Workbook

Sheet README
A1: US CPI (Sep 2026) Pre-Event Model｜美国9月CPI发布前模型 v20261013-1803
A2: Release 发布: Wed 2026-10-14 08:30 ET = 20:30 SGT. Pre-event snapshot locked 2026-10-13 18:03 SGT — do not edit; post-event values go in 'LiveChecklist' Actual column only.
A3: Yellow cells = assumptions/inputs (黄色=假设). All other numbers are formulas or sourced data.
A4: Sheets: Consensus · BaseEffect · Scenarios · Reaction · Valuation · LiveChecklist · SourceLedger · AssumptionRegister · ModelProvenance · Changelog
A5: Not investment advice｜非投资建议

Sheet Consensus
A1: Measure 指标 | B1: Prior Aug 前值 | C1: Consensus 共识 | D1: Range low | E1: Range high | F1: OS hypothesis 我们 | G1: Gap OS−Cons (pp) | H1: Source 来源
A2: Headline CPI MoM % | B2: 0.4 | C2: 0.6 | D2: 0.5 | E2: 0.7 | F2: 0.58 | G2: =F2-C2 | H2: FinancialJuice 10/12; TD 10/9 (FactSet 0.5)
A3: Headline CPI YoY % | B3: 3.4 | C3: 3.6 | D3: 3.5 | E3: 3.8 | F3: 3.6 | G3: =F3-C3 | H3: FinancialJuice 10/12; TD 10/9; FactSet
A4: Core CPI MoM % | B4: 0.3 | C4: 0.2 | D4: 0.2 | E4: 0.3 | F4: 0.22 | G4: =F4-C4 | H4: FinancialJuice 10/12; TD 10/9; FactSet
A5: Core CPI YoY % | B5: 2.4 | C5: 2.5 | D5: 2.3 | E5: 2.6 | F5: 2.4 | G5: =F5-C5 | H5: TD/FJ 2.5 vs FactSet 2.4 (CONFLICT logged)

Sheet BaseEffect
A1: Item 项目 | B1: Headline 整体 | C1: Core 核心 | D1: Note 说明
A2: Index Aug-2026 (SA, FRED) | B2: 334.131 | C2: 337.765 | D2: FRED CPIAUCSL / CPILFESL
A3: Index Sep-2025 (SA, FRED) | B3: 324.245 | C3: 330.418 | D3: base month 基期
A4: Assumed Sep MoM % 假设环比 | B4: 0.58 | C4: 0.22 | D4: INPUT — change to test 修改测试
A5: Implied Sep-2026 index | B5: =B2*(1+B4/100) | C5: =C2*(1+C4/100) | D5: formula
A6: Implied YoY % (SA approx.) | B6: =(B5/B3-1)*100 | C6: =(C5/C3-1)*100 | D6: official YoY uses NSA — ±0.05pp
A7: Index Jun-2026 | B7: 332.568 | C7: 336.065 | D7: for 3m annualised
A8: 3m annualised % 三个月年化 | B8: =((B5/B7)^4-1)*100 | C8: =((C5/C7)^4-1)*100 | D8: Jun weak base drops out → jumps
A9: Core MoM needed for YoY to round to 2.5% (≥2.45) | C9: =((C3*1.0245)/C2-1)*100 | D9: break-even 临界

Sheet Scenarios
A1: Scenario 情景 | B1: Core MoM range | C1: Prob 概率 | D1: Core MoM point | E1: Δ2Y bp | F1: Δ10Y bp | G1: ΔUSDJPY ¥ | H1: ΔNDX % | I1: ΔSOX % | J1: Oct hike odds %
A2: Cool 偏冷 | B2: ≤0.15 | C2: 0.25 | D2: 0.12 | E2: -10 | F2: -7 | G2: -0.8 | H2: 1.1 | I2: 1.8 | J2: 10
A3: Inline 符合 | B3: 0.16–0.24 | C3: 0.5 | D3: 0.2 | E3: 0 | F3: 0 | G3: 0 | H3: 0 | I3: 0 | J3: 18
A4: Hot 偏热 | B4: ≥0.25 | C4: 0.25 | D4: 0.3 | E4: 12 | F4: 8 | G4: 0.8 | H4: -1.5 | I4: -2.3 | J4: 32
A5: Prob-weighted 概率加权 | C5: =SUM(C2:C4) | D5: =SUMPRODUCT($C$2:$C$4,D2:D4) | E5: =SUMPRODUCT($C$2:$C$4,E2:E4) | F5: =SUMPRODUCT($C$2:$C$4,F2:F4) | G5: =SUMPRODUCT($C$2:$C$4,G2:G4) | H5: =SUMPRODUCT($C$2:$C$4,H2:H4) | I5: =SUMPRODUCT($C$2:$C$4,I2:I4) | J5: =SUMPRODUCT($C$2:$C$4,J2:J4)
A6: Check: probs sum to 1 | C6: =IF(ABS(C5-1)<0.0001,"OK","FIX")
A7: Market pricing (Kalshi, 10/13): Oct hike ≈20%, Dec ≈73% — MARKET EXPECTATION, predictionauthority.com

Sheet Reaction
A1: Ticker | B1: Beta %/+10bp 10Y (DATA) | C1: Corr | D1: R² | E1: Price 10/12 | F1: Cool Δ10Y→% | G1: Inline | H1: Hot Δ10Y→% | I1: Hot $ move/share
A2: SPCX | B2: -2.558 | C2: -0.2 | D2: =C2^2 | E2: 163.42 | F2: =B2*Scenarios!$F$2/10 | G2: =B2*Scenarios!$F$3/10 | H2: =B2*Scenarios!$F$4/10 | I2: =E2*H2/100
A3: TSLA | B3: -0.871 | C3: -0.123 | D3: =C3^2 | E3: 378.03 | F3: =B3*Scenarios!$F$2/10 | G3: =B3*Scenarios!$F$3/10 | H3: =B3*Scenarios!$F$4/10 | I3: =E3*H3/100
A4: NVDA | B4: -0.438 | C4: -0.075 | D4: =C4^2 | E4: 226.32 | F4: =B4*Scenarios!$F$2/10 | G4: =B4*Scenarios!$F$3/10 | H4: =B4*Scenarios!$F$4/10 | I4: =E4*H4/100
A5: MU | B5: -0.735 | C5: -0.059 | D5: =C5^2 | E5: 989.04 | F5: =B5*Scenarios!$F$2/10 | G5: =B5*Scenarios!$F$3/10 | H5: =B5*Scenarios!$F$4/10 | I5: =E5*H5/100
A6: GLW | B6: -1.492 | C6: -0.132 | D6: =C6^2 | E6: 147.28 | F6: =B6*Scenarios!$F$2/10 | G6: =B6*Scenarios!$F$3/10 | H6: =B6*Scenarios!$F$4/10 | I6: =E6*H6/100
A7: ARM | B7: -2.563 | C7: -0.208 | D7: =C7^2 | E7: 255.24 | F7: =B7*Scenarios!$F$2/10 | G7: =B7*Scenarios!$F$3/10 | H7: =B7*Scenarios!$F$4/10 | I7: =E7*H7/100
A8: AAPL | B8: -0.451 | C8: -0.119 | D8: =C8^2 | E8: 340.97 | F8: =B8*Scenarios!$F$2/10 | G8: =B8*Scenarios!$F$3/10 | H8: =B8*Scenarios!$F$4/10 | I8: =E8*H8/100
A9: TSM | B9: -0.709 | C9: -0.114 | D9: =C9^2 | E9: 444.35 | F9: =B9*Scenarios!$F$2/10 | G9: =B9*Scenarios!$F$3/10 | H9: =B9*Scenarios!$F$4/10 | I9: =E9*H9/100
A10: AVGO | B10: -0.754 | C10: -0.104 | D10: =C10^2 | E10: 354.73 | F10: =B10*Scenarios!$F$2/10 | G10: =B10*Scenarios!$F$3/10 | H10: =B10*Scenarios!$F$4/10 | I10: =E10*H10/100
A11: QCOM | B11: -1.156 | C11: -0.138 | D11: =C11^2 | E11: 174.43 | F11: =B11*Scenarios!$F$2/10 | G11: =B11*Scenarios!$F$3/10 | H11: =B11*Scenarios!$F$4/10 | I11: =E11*H11/100
A12: MRVL | B12: -1.84 | C12: -0.151 | D12: =C12^2 | E12: 265.86 | F12: =B12*Scenarios!$F$2/10 | G12: =B12*Scenarios!$F$3/10 | H12: =B12*Scenarios!$F$4/10 | I12: =E12*H12/100
A13: INTC | B13: -1.531 | C13: -0.129 | D13: =C13^2 | E13: 101.35 | F13: =B13*Scenarios!$F$2/10 | G13: =B13*Scenarios!$F$3/10 | H13: =B13*Scenarios!$F$4/10 | I13: =E13*H13/100
... A30: ^SOX | B30: -0.891 | C30: -0.127 | D30: =C30^2 | E30: 12236.79 | F30: =B30*Scenarios!$F$2/10 | G30: =B30*Scenarios!$F$3/10 | H30: =B30*Scenarios!$F$4/10 | I30: =E30*H30/100
A31: Method: OLS of daily return on daily Δ^TNX (bp), 2025-10 → 2026-10-12, Yahoo closes. Rate-only component; ignores Industry/AI & positioning terms. Low R² ⇒ low reliability.

Sheet Valuation
A1: Ticker | B1: Price | C1: Base DCF/sh (OS model) | D1: WACC (OS model) | E1: g∞ assumption | F1: ΔWACC from Hot (bp) | G1: ΔValue % ≈ −ΔWACC/(WACC−g) | H1: Price-implied Y1 growth | I1: Consensus FY+1 growth | J1: Implied − Consensus (pp)
A2: SPCX | B2: 163.42 | C2: 131.31 | D2: 0.1172 | E2: 0.03 | F2: =Scenarios!$F$4 | G2: =-(F2/10000)/(D2-E2)*100 | H2: 1.0779675 | I2: 1 | J2: =IF(OR(H2="",I2=""),"",(H2-I2)*100)
A3: TSLA | B3: 378.03 | C3: 44.2 | D3: 0.1322 | E3: 0.03 | F3: =Scenarios!$F$4 | G3: =-(F3/10000)/(D3-E3)*100 | H3: 0.8091475 | I3: 0.1362 | J3: =IF(OR(H3="",I3=""),"",(H3-I3)*100)
A4: NVDA | B4: 226.32 | C4: 549.25 | D4: 0.1322 | E4: 0.03 | F4: =Scenarios!$F$4 | G4: =-(F4/10000)/(D4-E4)*100 | H4: 0.40966915 | I4: 0.6815 | J4: =IF(OR(H4="",I4=""),"",(H4-I4)*100)
A5: MU | B5: 989.04 | C5: 584.92 | D5: 0.1322 | E5: 0.03 | F5: =Scenarios!$F$4 | G5: =-(F5/10000)/(D5-E5)*100 | H5: 0.30566557 | I5: 0.1573 | J5: =IF(OR(H5="",I5=""),"",(H5-I5)*100)
A6: GLW | B6: 147.28 | C6: 66.29 | D6: 0.10835 | E6: 0.03 | F6: =Scenarios!$F$4 | G6: =-(F6/10000)/(D6-E6)*100 | H6: 0.39662878 | I6: 0.19639999 | J6: =IF(OR(H6="",I6=""),"",(H6-I6)*100)
A7: ARM | B7: 255.24 | C7: 67.44 | D7: 0.1322 | E7: 0.03 | F7: =Scenarios!$F$4 | G7: =-(F7/10000)/(D7-E7)*100 | H7: 0.78061171 | I7: 0.3623 | J7: =IF(OR(H7="",I7=""),"",(H7-I7)*100)
A8: AAPL | B8: 340.97 | C8: 153.94 | D8: 0.10565 | E8: 0.03 | F8: =Scenarios!$F$4 | G8: =-(F8/10000)/(D8-E8)*100 | H8: 0.31421212 | I8: 0.10560001 | J8: =IF(OR(H8="",I8=""),"",(H8-I8)*100)
A9: TSM | B9: 444.35 | C9: 350.14 | D9: 0.11415 | E9: 0.03 | F9: =Scenarios!$F$4 | G9: =-(F9/10000)/(D9-E9)*100 | H9: 0.42901347 | I9: 0.35900003 | J9: =IF(OR(H9="",I9=""),"",(H9-I9)*100)
A10: AVGO | B10: 354.73 | C10: 774.32 | D10: 0.126 | E10: 0.03 | F10: =Scenarios!$F$4 | G10: =-(F10/10000)/(D10-E10)*100 | H10: 0.40882594 | I10: 0.64129996 | J10: =IF(OR(H10="",I10=""),"",(H10-I10)*100)
A11: QCOM | B11: 174.43 | C11: 103.73 | D11: 0.1322 | E11: 0.03 | F11: =Scenarios!$F$4 | G11: =-(F11/10000)/(D11-E11)*100 | H11: 0.17865846 | I11: 0.0475 | J11: =IF(OR(H11="",I11=""),"",(H11-I11)*100)
A12: MRVL | B12: 265.86 | C12: 256.08 | D12: 0.1322 | E12: 0.03 | F12: =Scenarios!$F$4 | G12: =-(F12/10000)/(D12-E12)*100 | H12: 0.64315497 | I12: 0.6315 | J12: =IF(OR(H12="",I12=""),"",(H12-I12)*100)
A13: INTC | B13: 101.35 | C13: 12.03 | D13: 0.1322 | E13: 0.03 | F13: =Scenarios!$F$4 | G13: =-(F13/10000)/(D13-E13)*100 | H13: 0.68930431 | I13: 0.14899999 | J13: =IF(OR(H13="",I13=""),"",(H13-I13)*100)
... A28: MXL | B28: 88.99 | C28: 22.35 | D28: 0.1322 | E28: 0.03 | F28: =Scenarios!$F$4 | G28: =-(F28/10000)/(D28-E28)*100 | H28: 0.68965392 | I28: 0.2988 | J28: =IF(OR(H28="",I28=""),"",(H28-I28)*100)
A29: Approximation (HYPOTHESIS): perpetuity duration 1/(WACC−g). Long-run fair-value effect of a lasting discount-rate change — NOT a one-day price forecast. Source: OS company models v20261013-1622

Sheet LiveChecklist
A1: No. | B1: Item 观察项 | C1: Cool if | D1: Hot if | E1: Actual 实际 (fill at 20:30 SGT) | F1: Read 判读 | G1: Teaching 教学
A2: 1 | B2: Core MoM % (2 decimals) | C2: 0.15 | D2: 0.25 | F2: =IF(E2="","",IF(E2<=C2,"COOL",IF(E2>=D2,"HOT","INLINE"))) | G2: Fed watches core: food & energy are volatile 核心剔除食品能源
A3: 2 | B3: Core YoY % | C3: 2.35 | D3: 2.55 | F3: =IF(E3="","",IF(E3<=C3,"COOL",IF(E3>=D3,"HOT","INLINE"))) | G3: 2.4 vs 2.5 is the headline-writer's split
A4: 3 | B4: Supercore MoM % (core services ex-shelter) | C4: 0.2 | D4: 0.35 | F4: =IF(E4="","",IF(E4<=C4,"COOL",IF(E4>=D4,"HOT","INLINE"))) | G4: wage-driven services = sticky 粘性
A5: 4 | B5: Shelter MoM % | C5: 0.25 | D5: 0.35 | F5: =IF(E5="","",IF(E5<=C5,"COOL",IF(E5>=D5,"HOT","INLINE"))) | G5: ~1/3 of CPI; moves slowly
A6: 5 | B6: Core goods MoM % | C6: 0 | D6: 0.2 | F6: =IF(E6="","",IF(E6<=C6,"COOL",IF(E6>=D6,"HOT","INLINE"))) | G6: tariff / supply pass-through
A7: 6 | B7: Headline MoM % | C7: 0.45 | D7: 0.7 | F7: =IF(E7="","",IF(E7<=C7,"COOL",IF(E7>=D7,"HOT","INLINE"))) | G7: energy-driven; bonds may look through
A8: 7 | B8: Δ2Y first 15 min (bp) | C8: -8 | D8: 8 | F8: =IF(E8="","",IF(E8<=C8,"COOL",IF(E8>=D8,"HOT","INLINE"))) | G8: |Δ|<3bp ⇒ already priced
A9: 8 | B9: Δ10Y first 2h (bp) | C9: -6 | D9: 6 | F9: =IF(E9="","",IF(E9<=C9,"COOL",IF(E9>=D9,"HOT","INLINE"))) | G9: hot core + 10Y down ⇒ growth fear (falsifier)
A10: 9 | B10: USD/JPY level | C10: 157 | D10: 159.5 | F10: =IF(E10="","",IF(E10<=C10,"COOL",IF(E10>=D10,"HOT","INLINE"))) | G10: near 2024 intervention zone (~160)
A11: 10 | B11: Oct hike odds % (CME/Kalshi) | C11: 12 | D11: 30 | F11: =IF(E11="","",IF(E11<=C11,"COOL",IF(E11>=D11,"HOT","INLINE"))) | G11: ≥30% ⇒ Oct 28 meeting 'live'
A12: 11 | B12: Surprise core = Actual − 0.20 | F12: =IF(E2="","",E2-0.2) | G12: Surprise = Actual − Expected

Sheet SourceLedger
A1: No. | B1: Source 来源 | C1: What 内容 | D1: Published/Fetched | E1: Claim class
A2: 1 | B2: BLS release schedule 2026 (bls.gov/schedule/2026) via OS calendar | C2: CPI Sep 2026 on 10/14 08:30 ET | D2: OS calendar 2026-10-13 | E2: FACT (CONFIRMED)
A3: 2 | B3: FRED CPIAUCSL, CPILFESL, PCEPILFE, UNRATE, PAYEMS, DFEDTARU, DGS2, DGS10, DFII10, T10YIE | C3: Index levels, Fed upper bound 4.00%, 2Y 4.75%, 10Y 5.22% (10/8) | D3: fetched 2026-10-13 16:22 SGT | E3: DATA
A4: 3 | B4: Yahoo Finance (^TNX, JPY=X, ^SOX, ^NDX, ^KS11, CL=F, ^VIX, 27 watchlist closes) | C4: Market levels & 1Y daily history | D4: fetched 2026-10-13 16:22 SGT | E4: DATA
A5: 4 | B5: FinancialJuice 'US CPI Prep (14th October)' | C5: Consensus & ranges; DB 0.16 / WF 0.20 / CA 0.20 core forecasts | D5: 2026-10-12 | E5: MARKET EXPECTATION
A6: 5 | B6: TD Economics weekly (via stockmarkethours.org / tlines.tech) | C6: Consensus 0.6/3.6/0.2/2.5 | D6: 2026-10-09 | E6: MARKET EXPECTATION
A7: 6 | B7: Morningstar (FactSet consensus) | C7: 0.5/3.6/0.2/2.4 | D7: ~2026-10-12 | E7: MARKET EXPECTATION (date text conflict logged)
A8: 7 | B8: predictionauthority.com (Kalshi) | C8: Oct hike ≈20%, Dec ≈73%; 10Y 5.28–5.31% near 24-yr high | D8: 2026-10-09, odds 10/13 | E8: MARKET EXPECTATION (secondary)
A9: 8 | B9: Kiplinger / onetrader / vanderbiltreport weekly calendars | C9: Bowman 05:40 ET, Barkin 13:30 ET, Beige Book 14:00 ET (10/14); Warsh 23:30 ET 10/15 | D9: 2026-10-09 to 10-11 | E9: FACT (secondary, TENTATIVE times)
A10: 9 | B10: AP / Herald / Chosun / Seoul Economic Daily | C10: KOSPI −5.46% to 6,035 on 10/13; CXMT DRAM fears; foreign net selling | D10: 2026-10-13 | E10: FACT (news)
A11: 10 | B11: TSMC IR | C11: 3Q26 conference Thu 10/15 14:00 Taiwan (=14:00 SGT) | D11: IR page | E11: FACT (CONFIRMED)
A12: 11 | B12: gobull.ai / thesiliconledger / hulicalendar | C12: ASML Q3 results 10/14 07:00 Amsterdam | D12: 2026-10-09 to 10-12 | E12: FACT (secondary)
A13: 12 | B13: OS company models v20261013 | C13: WACC, Base DCF, price-implied growth | D13: v20261013-1622 | E13: HYPOTHESIS (model)

Sheet AssumptionRegister
A1: ID | B1: Assumption 假设 | C1: Value | D1: Why 依据 | E1: Falsifier 证伪
A2: A1 | B2: OS core MoM hypothesis | C2: 0.22% | D2: consensus 0.2; DB 0.16 vs shelter/medical rebound + airfares from jet fuel | E2: core ≤0.15 or ≥0.25
A3: A2 | B3: Scenario probabilities | C3: 25/50/25 | D3: bank forecast dispersion 0.16–0.20, range 0.2–0.3 | E3: post-mortem calibration after 3+ prints
A4: A3 | B4: Reaction ranges (2Y/10Y/NDX/SOX/JPY) | C4: see Scenarios | D4: judgement; not back-tested in OS | E4: actual moves outside range ⇒ widen
A5: A4 | B5: Yield beta stable over next 2 days | C5: Reaction sheet | D5: 1Y OLS; R² ≤0.12 | E5: beta sign flips on the day
A6: A5 | B6: g∞ terminal growth | C6: 3% | D6: OS model convention | E6: —
A7: A6 | B7: ΔWACC = Δ10Y one-for-one | C7: Hot +8bp | D7: risk-free component only | E7: ERP moves offset
A8: A7 | B8: US DST in force (SGT = ET + 12h) | C8: until 2026-11-01 | D8: US DST ends 1st Sunday Nov | E8: —

Sheet ModelProvenance
A1: Item | B1: Detail
A2: Builder | B2: build_xlsx.py / build_charts.py / build_docs.py (box /workspace/cpi_prep), run v20261013-1803
A3: Inputs | B3: FRED+Yahoo snapshot data/latest (20261013-1622); web sources per SourceLedger
A4: Known issue | B4: OS dashboard CPI YoY uses 12-row lag; Oct-2025 index missing (shutdown) ⇒ dashboard shows CPI 3.71% / core 2.76% vs correct 3.35% / 2.45% (Aug). This book uses calendar-matched YoY. Pipeline fix pending.
A5: Lock | B5: PRE_EVENT_SNAPSHOT json sha256 recorded; file set read-only after build

Sheet Changelog
A1: Version | B1: Change
A2: v20261013-1803 | B2: Initial pre-event snapshot for US CPI (Sep 2026). Post-event review → next Daily OS update.
