Workbook

Sheet README
A1: CRWD Valuation Model｜估值模型 — as of 2026-10-13 18:12 SGT
A2: Live formulas: yellow = ASSUMPTION input (editable), blue = DATA (sourced in Sources sheet). Change any yellow cell and every sheet recalculates.
A3: 黄色=假设(可改)，蓝色=数据(来源见Sources表)。所有估值、反向DCF、敏感度、情景、2/4/6/8季度检验均为公式联动。
A4: Not investment advice｜非投资建议。
A5: Sheets: Inputs, Scenarios, DCF, ReverseDCF, Sensitivity, Horizons, SOTP, Comps, ROIC_WACC, History, Sources, Assumptions

Sheet Inputs
A1: Item 项目 | B1: Value 数值 | C1: Type | D1: Source 来源
A2: Price | B2: 263.01 | C2: DATA | D2: see Sources
A3: MarketCap | B3: 269305118720 | C3: DATA
A4: Cash | B4: 5013847040 | C4: DATA
A5: Debt | B5: 820179008 | C5: DATA
A6: RevenueTTM | B6: 5396145152 | C6: DATA
A7: FCF_TTM | B7: 1522603000 | C7: DATA
A8: FX_USD_per_FinCur | B8: 1 | C8: DATA
A9: RiskFree | B9: 0.0522 | C9: DATA
A10: Beta | B10: 1.197 | C10: DATA (clamped)
A11: ERP | B11: 0.05 | C11: ASSUMPTION
A12: TaxRate | B12: 0.18 | C12: ASSUMPTION
A13: Y1Growth_Base | B13: 0.22639999 | C13: DATA→consensus
A14: FCFMargin_Now | B14: =MAX(B7/B6,-0.5) | C14: FORMULA
A15: LongRunMargin_Base | B15: 0.32 | C15: ASSUMPTION
A16: WACC_Base | B16: =B9+B10*B11 | C16: FORMULA
A17: NetCash | B17: =B4-B5 | C17: FORMULA
A18: EV_now (fin cur) | B18: =B3/B8-B4+B5 | C18: FORMULA

Sheet Scenarios
A1: Param | B1: Bear | C1: Base | D1: Bull | E1: Note
A2: Y1 growth | B2: =Inputs!B13*0.5 | C2: =Inputs!B13 | D2: =Inputs!B13*1.3 | E2: Bear 0.5x / Bull 1.3x consensus FY+1 growth (ASSUMPTION)
A3: LongRun FCF margin | B3: =Inputs!B15*0.8 | C3: =Inputs!B15 | D3: =Inputs!B15*1.15 | E3: Bear 0.8x / Bull 1.15x (ASSUMPTION)
A4: WACC | B4: =Inputs!B16+0.01 | C4: =Inputs!B16 | D4: =Inputs!B16-0.005
A5: Terminal g | B5: 0.025 | C5: 0.03 | D5: 0.035
A6: Probability | B6: 0.25 | C6: 0.5 | D6: 0.25
A7: Value/share (USD) | B7: =DCF!C40 | C7: =DCF!C41 | D7: =DCF!C42
A8: Upside vs price | B8: =B7/Inputs!$B$2-1 | C8: =C7/Inputs!$B$2-1 | D8: =D7/Inputs!$B$2-1
A9: Prob-weighted value | C9: =SUMPRODUCT(B6:D6,B7:D7)
A10: Weighted upside | C10: =C9/Inputs!B2-1

Sheet DCF
A1: 10-year FCF DCF per scenario (financial currency); growth fades linearly to terminal g; margin moves linearly to long-run by Y5
A3: Bear
A4: Year | B4: 1 | C4: 2 | D4: 3 | E4: 4 | F4: 5 | G4: 6 | H4: 7 | I4: 8 | J4: 9 | K4: 10
A5: Growth | B5: =Scenarios!B2-(Scenarios!B2-Scenarios!B5)*(B4-1)/9 | C5: =Scenarios!B2-(Scenarios!B2-Scenarios!B5)*(C4-1)/9 | D5: =Scenarios!B2-(Scenarios!B2-Scenarios!B5)*(D4-1)/9 | E5: =Scenarios!B2-(Scenarios!B2-Scenarios!B5)*(E4-1)/9 | F5: =Scenarios!B2-(Scenarios!B2-Scenarios!B5)*(F4-1)/9 | G5: =Scenarios!B2-(Scenarios!B2-Scenarios!B5)*(G4-1)/9 | H5: =Scenarios!B2-(Scenarios!B2-Scenarios!B5)*(H4-1)/9 | I5: =Scenarios!B2-(Scenarios!B2-Scenarios!B5)*(I4-1)/9 | J5: =Scenarios!B2-(Scenarios!B2-Scenarios!B5)*(J4-1)/9 | K5: =Scenarios!B2-(Scenarios!B2-Scenarios!B5)*(K4-1)/9
A6: Revenue | B6: =Inputs!B6*(1+B5) | C6: =B6*(1+C5) | D6: =C6*(1+D5) | E6: =D6*(1+E5) | F6: =E6*(1+F5) | G6: =F6*(1+G5) | H6: =G6*(1+H5) | I6: =H6*(1+I5) | J6: =I6*(1+J5) | K6: =J6*(1+K5)
A7: FCF margin | B7: =Inputs!$B$14+(Scenarios!B3-Inputs!$B$14)*MIN(B4,5)/5 | C7: =Inputs!$B$14+(Scenarios!B3-Inputs!$B$14)*MIN(C4,5)/5 | D7: =Inputs!$B$14+(Scenarios!B3-Inputs!$B$14)*MIN(D4,5)/5 | E7: =Inputs!$B$14+(Scenarios!B3-Inputs!$B$14)*MIN(E4,5)/5 | F7: =Inputs!$B$14+(Scenarios!B3-Inputs!$B$14)*MIN(F4,5)/5 | G7: =Inputs!$B$14+(Scenarios!B3-Inputs!$B$14)*MIN(G4,5)/5 | H7: =Inputs!$B$14+(Scenarios!B3-Inputs!$B$14)*MIN(H4,5)/5 | I7: =Inputs!$B$14+(Scenarios!B3-Inputs!$B$14)*MIN(I4,5)/5 | J7: =Inputs!$B$14+(Scenarios!B3-Inputs!$B$14)*MIN(J4,5)/5 | K7: =Inputs!$B$14+(Scenarios!B3-Inputs!$B$14)*MIN(K4,5)/5
A8: FCF | B8: =B6*B7 | C8: =C6*C7 | D8: =D6*D7 | E8: =E6*E7 | F8: =F6*F7 | G8: =G6*G7 | H8: =H6*H7 | I8: =I6*I7 | ... K8: =K6*K7
A9: Disc factor | B9: =1/(1+Scenarios!B4)^B4 | C9: =1/(1+Scenarios!B4)^C4 | D9: =1/(1+Scenarios!B4)^D4 | E9: =1/(1+Scenarios!B4)^E4 | F9: =1/(1+Scenarios!B4)^F4 | G9: =1/(1+Scenarios!B4)^G4 | H9: =1/(1+Scenarios!B4)^H4 | I9: =1/(1+Scenarios!B4)^I4 | J9: =1/(1+Scenarios!B4)^J4 | K9: =1/(1+Scenarios!B4)^K4
A10: PV FCF | B10: =B8*B9 | C10: =C8*C9 | D10: =D8*D9 | E10: =E8*E9 | F10: =F8*F9 | G10: =G8*G9 | H10: =H8*H9 | I10: =I8*I9 | ... K10: =K8*K9
A11: Sum PV / TV / PV TV / EV / Equity | B11: =SUM(B10:K10) | C11: =K8*(1+Scenarios!B5)/(Scenarios!B4-Scenarios!B5) | D11: =C11*K9 | E11: =B11+D11 | F11: =E11+Inputs!$B$17
A15: Base
A16: Year | B16: 1 | C16: 2 | D16: 3 | E16: 4 | F16: 5 | G16: 6 | H16: 7 | I16: 8 | J16: 9 | K16: 10
A17: Growth | B17: =Scenarios!C2-(Scenarios!C2-Scenarios!C5)*(B16-1)/9 | C17: =Scenarios!C2-(Scenarios!C2-Scenarios!C5)*(C16-1)/9 | D17: =Scenarios!C2-(Scenarios!C2-Scenarios!C5)*(D16-1)/9 | E17: =Scenarios!C2-(Scenarios!C2-Scenarios!C5)*(E16-1)/9 | F17: =Scenarios!C2-(Scenarios!C2-Scenarios!C5)*(F16-1)/9 | G17: =Scenarios!C2-(Scenarios!C2-Scenarios!C5)*(G16-1)/9 | H17: =Scenarios!C2-(Scenarios!C2-Scenarios!C5)*(H16-1)/9 | I17: =Scenarios!C2-(Scenarios!C2-Scenarios!C5)*(I16-1)/9 | J17: =Scenarios!C2-(Scenarios!C2-Scenarios!C5)*(J16-1)/9 | K17: =Scenarios!C2-(Scenarios!C2-Scenarios!C5)*(K16-1)/9
A18: Revenue | B18: =Inputs!B6*(1+B17) | C18: =B18*(1+C17) | D18: =C18*(1+D17) | E18: =D18*(1+E17) | F18: =E18*(1+F17) | G18: =F18*(1+G17) | H18: =G18*(1+H17) | I18: =H18*(1+I17) | J18: =I18*(1+J17) | K18: =J18*(1+K17)
A19: FCF margin | B19: =Inputs!$B$14+(Scenarios!C3-Inputs!$B$14)*MIN(B16,5)/5 | C19: =Inputs!$B$14+(Scenarios!C3-Inputs!$B$14)*MIN(C16,5)/5 | D19: =Inputs!$B$14+(Scenarios!C3-Inputs!$B$14)*MIN(D16,5)/5 | E19: =Inputs!$B$14+(Scenarios!C3-Inputs!$B$14)*MIN(E16,5)/5 | F19: =Inputs!$B$14+(Scenarios!C3-Inputs!$B$14)*MIN(F16,5)/5 | G19: =Inputs!$B$14+(Scenarios!C3-Inputs!$B$14)*MIN(G16,5)/5 | H19: =Inputs!$B$14+(Scenarios!C3-Inputs!$B$14)*MIN(H16,5)/5 | I19: =Inputs!$B$14+(Scenarios!C3-Inputs!$B$14)*MIN(I16,5)/5 | J19: =Inputs!$B$14+(Scenarios!C3-Inputs!$B$14)*MIN(J16,5)/5 | K19: =Inputs!$B$14+(Scenarios!C3-Inputs!$B$14)*MIN(K16,5)/5
A20: FCF | B20: =B18*B19 | C20: =C18*C19 | D20: =D18*D19 | E20: =E18*E19 | F20: =F18*F19 | G20: =G18*G19 | H20: =H18*H19 | I20: =I18*I19 | ... K20: =K18*K19
A21: Disc factor | B21: =1/(1+Scenarios!C4)^B16 | C21: =1/(1+Scenarios!C4)^C16 | D21: =1/(1+Scenarios!C4)^D16 | E21: =1/(1+Scenarios!C4)^E16 | F21: =1/(1+Scenarios!C4)^F16 | G21: =1/(1+Scenarios!C4)^G16 | H21: =1/(1+Scenarios!C4)^H16 | I21: =1/(1+Scenarios!C4)^I16 | J21: =1/(1+Scenarios!C4)^J16 | K21: =1/(1+Scenarios!C4)^K16
A22: PV FCF | B22: =B20*B21 | C22: =C20*C21 | D22: =D20*D21 | E22: =E20*E21 | F22: =F20*F21 | G22: =G20*G21 | H22: =H20*H21 | I22: =I20*I21 | ... K22: =K20*K21
A23: Sum PV / TV / PV TV / EV / Equity | B23: =SUM(B22:K22) | C23: =K20*(1+Scenarios!C5)/(Scenarios!C4-Scenarios!C5) | D23: =C23*K21 | E23: =B23+D23 | F23: =E23+Inputs!$B$17
A27: Bull
A28: Year | B28: 1 | C28: 2 | D28: 3 | E28: 4 | F28: 5 | G28: 6 | H28: 7 | I28: 8 | J28: 9 | K28: 10
A29: Growth | B29: =Scenarios!D2-(Scenarios!D2-Scenarios!D5)*(B28-1)/9 | C29: =Scenarios!D2-(Scenarios!D2-Scenarios!D5)*(C28-1)/9 | D29: =Scenarios!D2-(Scenarios!D2-Scenarios!D5)*(D28-1)/9 | E29: =Scenarios!D2-(Scenarios!D2-Scenarios!D5)*(E28-1)/9 | F29: =Scenarios!D2-(Scenarios!D2-Scenarios!D5)*(F28-1)/9 | G29: =Scenarios!D2-(Scenarios!D2-Scenarios!D5)*(G28-1)/9 | H29: =Scenarios!D2-(Scenarios!D2-Scenarios!D5)*(H28-1)/9 | I29: =Scenarios!D2-(Scenarios!D2-Scenarios!D5)*(I28-1)/9 | J29: =Scenarios!D2-(Scenarios!D2-Scenarios!D5)*(J28-1)/9 | K29: =Scenarios!D2-(Scenarios!D2-Scenarios!D5)*(K28-1)/9
A30: Revenue | B30: =Inputs!B6*(1+B29) | C30: =B30*(1+C29) | D30: =C30*(1+D29) | E30: =D30*(1+E29) | F30: =E30*(1+F29) | G30: =F30*(1+G29) | H30: =G30*(1+H29) | I30: =H30*(1+I29) | J30: =I30*(1+J29) | K30: =J30*(1+K29)
A31: FCF margin | B31: =Inputs!$B$14+(Scenarios!D3-Inputs!$B$14)*MIN(B28,5)/5 | C31: =Inputs!$B$14+(Scenarios!D3-Inputs!$B$14)*MIN(C28,5)/5 | D31: =Inputs!$B$14+(Scenarios!D3-Inputs!$B$14)*MIN(D28,5)/5 | E31: =Inputs!$B$14+(Scenarios!D3-Inputs!$B$14)*MIN(E28,5)/5 | F31: =Inputs!$B$14+(Scenarios!D3-Inputs!$B$14)*MIN(F28,5)/5 | G31: =Inputs!$B$14+(Scenarios!D3-Inputs!$B$14)*MIN(G28,5)/5 | H31: =Inputs!$B$14+(Scenarios!D3-Inputs!$B$14)*MIN(H28,5)/5 | I31: =Inputs!$B$14+(Scenarios!D3-Inputs!$B$14)*MIN(I28,5)/5 | J31: =Inputs!$B$14+(Scenarios!D3-Inputs!$B$14)*MIN(J28,5)/5 | K31: =Inputs!$B$14+(Scenarios!D3-Inputs!$B$14)*MIN(K28,5)/5
A32: FCF | B32: =B30*B31 | C32: =C30*C31 | D32: =D30*D31 | E32: =E30*E31 | F32: =F30*F31 | G32: =G30*G31 | H32: =H30*H31 | I32: =I30*I31 | ... K32: =K30*K31
A33: Disc factor | B33: =1/(1+Scenarios!D4)^B28 | C33: =1/(1+Scenarios!D4)^C28 | D33: =1/(1+Scenarios!D4)^D28 | E33: =1/(1+Scenarios!D4)^E28 | F33: =1/(1+Scenarios!D4)^F28 | G33: =1/(1+Scenarios!D4)^G28 | H33: =1/(1+Scenarios!D4)^H28 | I33: =1/(1+Scenarios!D4)^I28 | J33: =1/(1+Scenarios!D4)^J28 | K33: =1/(1+Scenarios!D4)^K28
A34: PV FCF | B34: =B32*B33 | C34: =C32*C33 | D34: =D32*D33 | E34: =E32*E33 | F34: =F32*F33 | G34: =G32*G33 | H34: =H32*H33 | I34: =I32*I33 | ... K34: =K32*K33
A35: Sum PV / TV / PV TV / EV / Equity | B35: =SUM(B34:K34) | C35: =K32*(1+Scenarios!D5)/(Scenarios!D4-Scenarios!D5) | D35: =C35*K33 | E35: =B35+D35 | F35: =E35+Inputs!$B$17
A40: Bear value/share USD | C40: =F11*Inputs!$B$8/Inputs!$B$3*Inputs!$B$2
A41: Base value/share USD | C41: =F23*Inputs!$B$8/Inputs!$B$3*Inputs!$B$2
A42: Bull value/share USD | C42: =F35*Inputs!$B$8/Inputs!$B$3*Inputs!$B$2

Sheet ReverseDCF
A1: Reverse DCF｜反向DCF: Base margin/WACC/terminal; vary Y1 growth. Implied growth = first g whose value ≥ price. | O1: Implied Y1 growth 隐含增速 | P1: =IFERROR(INDEX(A4:A96,MATCH(Inputs!B2,M4:M96,1)+1),"out of grid")
O2: Consensus FY+1 growth | P2: =Inputs!B13
A3: Y1 g | B3: PV Y1 | C3: PV Y2 | D3: PV Y3 | E3: PV Y4 | F3: PV Y5 | G3: PV Y6 | H3: PV Y7 | I3: PV Y8 | J3: PV Y9 | K3: PV Y10 | L3: PV TV | M3: Value/share
A4: -0.3 | B4: =N4*(Inputs!$B$14+(Scenarios!$C$3-Inputs!$B$14)*MIN(1,5)/5)/(1+Scenarios!$C$4)^1 | C4: =O4*(Inputs!$B$14+(Scenarios!$C$3-Inputs!$B$14)*MIN(2,5)/5)/(1+Scenarios!$C$4)^2 | D4: =P4*(Inputs!$B$14+(Scenarios!$C$3-Inputs!$B$14)*MIN(3,5)/5)/(1+Scenarios!$C$4)^3 | E4: =Q4*(Inputs!$B$14+(Scenarios!$C$3-Inputs!$B$14)*MIN(4,5)/5)/(1+Scenarios!$C$4)^4 | F4: =R4*(Inputs!$B$14+(Scenarios!$C$3-Inputs!$B$14)*MIN(5,5)/5)/(1+Scenarios!$C$4)^5 | G4: =S4*(Inputs!$B$14+(Scenarios!$C$3-Inputs!$B$14)*MIN(6,5)/5)/(1+Scenarios!$C$4)^6 | H4: =T4*(Inputs!$B$14+(Scenarios!$C$3-Inputs!$B$14)*MIN(7,5)/5)/(1+Scenarios!$C$4)^7 | I4: =U4*(Inputs!$B$14+(Scenarios!$C$3-Inputs!$B$14)*MIN(8,5)/5)/(1+Scenarios!$C$4)^8 | J4: =V4*(Inputs!$B$14+(Scenarios!$C$3-Inputs!$B$14)*MIN(9,5)/5)/(1+Scenarios!$C$4)^9 | K4: =W4*(Inputs!$B$14+(Scenarios!$C$3-Inputs!$B$14)*MIN(10,5)/5)/(1+Scenarios!$C$4)^10 | L4: =W4*(Inputs!$B$14+(Scenarios!$C$3-Inputs!$B$14))*(1+Scenarios!$C$5)/(Scenarios!$C$4-Scenarios!$C$5)/(1+Scenarios!$C$4)^10 | M4: =(SUM(B4:L4)+Inputs!$B$17)*Inputs!$B$8/Inputs!$B$3*Inputs!$B$2 | N4: =Inputs!$B$6*(1+($A4-($A4-Scenarios!$C$5)*(1-1)/9)) | O4: =N4*(1+($A4-($A4-Scenarios!$C$5)*(2-1)/9)) | P4: =O4*(1+($A4-($A4-Scenarios!$C$5)*(3-1)/9)) | Q4: =P4*(1+($A4-($A4-Scenarios!$C$5)*(4-1)/9)) | R4: =Q4*(1+($A4-($A4-Scenarios!$C$5)*(5-1)/9)) | S4: =R4*(1+($A4-($A4-Scenarios!$C$5)*(6-1)/9)) | T4: =S4*(1+($A4-($A4-Scenarios!$C$5)*(7-1)/9)) | U4: =T4*(1+($A4-($A4-Scenarios!$C$5)*(8-1)/9)) | V4: =U4*(1+($A4-($A4-Scenarios!$C$5)*(9-1)/9)) | W4: =V4*(1+($A4-($A4-Scenarios!$C$5)*(10-1)/9))
A5: -0.275 | B5: =N5*(Inputs!$B$14+(Scenarios!$C$3-Inputs!$B$14)*MIN(1,5)/5)/(1+Scenarios!$C$4)^1 | C5: =O5*(Inputs!$B$14+(Scenarios!$C$3-Inputs!$B$14)*MIN(2,5)/5)/(1+Scenarios!$C$4)^2 | D5: =P5*(Inputs!$B$14+(Scenarios!$C$3-Inputs!$B$14)*MIN(3,5)/5)/(1+Scenarios!$C$4)^3 | E5: =Q5*(Inputs!$B$14+(Scenarios!$C$3-Inputs!$B$14)*MIN(4,5)/5)/(1+Scenarios!$C$4)^4 | F5: =R5*(Inputs!$B$14+(Scenarios!$C$3-Inputs!$B$14)*MIN(5,5)/5)/(1+Scenarios!$C$4)^5 | G5: =S5*(Inputs!$B$14+(Scenarios!$C$3-Inputs!$B$14)*MIN(6,5)/5)/(1+Scenarios!$C$4)^6 | H5: =T5*(Inputs!$B$14+(Scenarios!$C$3-Inputs!$B$14)*MIN(7,5)/5)/(1+Scenarios!$C$4)^7 | I5: =U5*(Inputs!$B$14+(Scenarios!$C$3-Inputs!$B$14)*MIN(8,5)/5)/(1+Scenarios!$C$4)^8 | J5: =V5*(Inputs!$B$14+(Scenarios!$C$3-Inputs!$B$14)*MIN(9,5)/5)/(1+Scenarios!$C$4)^9 | K5: =W5*(Inputs!$B$14+(Scenarios!$C$3-Inputs!$B$14)*MIN(10,5)/5)/(1+Scenarios!$C$4)^10 | L5: =W5*(Inputs!$B$14+(Scenarios!$C$3-Inputs!$B$14))*(1+Scenarios!$C$5)/(Scenarios!$C$4-Scenarios!$C$5)/(1+Scenarios!$C$4)^10 | M5: =(SUM(B5:L5)+Inputs!$B$17)*Inputs!$B$8/Inputs!$B$3*Inputs!$B$2 | N5: =Inputs!$B$6*(1+($A5-($A5-Scenarios!$C$5)*(1-1)/9)) | O5: =N5*(1+($A5-($A5-Scenarios!$C$5)*(2-1)/9)) | P5: =O5*(1+($A5-($A5-Scenarios!$C$5)*(3-1)/9)) | Q5: =P5*(1+($A5-($A5-Scenarios!$C$5)*(4-1)/9)) | R5: =Q5*(1+($A5-($A5-Scenarios!$C$5)*(5-1)/9)) | S5: =R5*(1+($A5-($A5-Scenarios!$C$5)*(6-1)/9)) | T5: =S5*(1+($A5-($A5-Scenarios!$C$5)*(7-1)/9)) | U5: =T5*(1+($A5-($A5-Scenarios!$C$5)*(8-1)/9)) | V5: =U5*(1+($A5-($A5-Scenarios!$C$5)*(9-1)/9)) | W5: =V5*(1+($A5-($A5-Scenarios!$C$5)*(10-1)/9))
A6: -0.25 | B6: =N6*(Inputs!$B$14+(Scenarios!$C$3-Inputs!$B$14)*MIN(1,5)/5)/(1+Scenarios!$C$4)^1 | C6: =O6*(Inputs!$B$14+(Scenarios!$C$3-Inputs!$B$14)*MIN(2,5)/5)/(1+Scenarios!$C$4)^2 | D6: =P6*(Inputs!$B$14+(Scenarios!$C$3-Inputs!$B$14)*MIN(3,5)/5)/(1+Scenarios!$C$4)^3 | E6: =Q6*(Inputs!$B$14+(Scenarios!$C$3-Inputs!$B$14)*MIN(4,5)/5)/(1+Scenarios!$C$4)^4 | F6: =R6*(Inputs!$B$14+(Scenarios!$C$3-Inputs!$B$14)*MIN(5,5)/5)/(1+Scenarios!$C$4)^5 | G6: =S6*(Inputs!$B$14+(Scenarios!$C$3-Inputs!$B$14)*MIN(6,5)/5)/(1+Scenarios!$C$4)^6 | H6: =T6*(Inputs!$B$14+(Scenarios!$C$3-Inputs!$B$14)*MIN(7,5)/5)/(1+Scenarios!$C$4)^7 | I6: =U6*(Inputs!$B$14+(Scenarios!$C$3-Inputs!$B$14)*MIN(8,5)/5)/(1+Scenarios!$C$4)^8 | J6: =V6*(Inputs!$B$14+(Scenarios!$C$3-Inputs!$B$14)*MIN(9,5)/5)/(1+Scenarios!$C$4)^9 | K6: =W6*(Inputs!$B$14+(Scenarios!$C$3-Inputs!$B$14)*MIN(10,5)/5)/(1+Scenarios!$C$4)^10 | L6: =W6*(Inputs!$B$14+(Scenarios!$C$3-Inputs!$B$14))*(1+Scenarios!$C$5)/(Scenarios!$C$4-Scenarios!$C$5)/(1+Scenarios!$C$4)^10 | M6: =(SUM(B6:L6)+Inputs!$B$17)*Inputs!$B$8/Inputs!$B$3*Inputs!$B$2 | N6: =Inputs!$B$6*(1+($A6-($A6-Scenarios!$C$5)*(1-1)/9)) | O6: =N6*(1+($A6-($A6-Scenarios!$C$5)*(2-1)/9)) | P6: =O6*(1+($A6-($A6-Scenarios!$C$5)*(3-1)/9)) | Q6: =P6*(1+($A6-($A6-Scenarios!$C$5)*(4-1)/9)) | R6: =Q6*(1+($A6-($A6-Scenarios!$C$5)*(5-1)/9)) | S6: =R6*(1+($A6-($A6-Scenarios!$C$5)*(6-1)/9)) | T6: =S6*(1+($A6-($A6-Scenarios!$C$5)*(7-1)/9)) | U6: =T6*(1+($A6-($A6-Scenarios!$C$5)*(8-1)/9)) | V6: =U6*(1+($A6-($A6-Scenarios!$C$5)*(9-1)/9)) | W6: =V6*(1+($A6-($A6-Scenarios!$C$5)*(10-1)/9))
A7: -0.225 | B7: =N7*(Inputs!$B$14+(Scenarios!$C$3-Inputs!$B$14)*MIN(1,5)/5)/(1+Scenarios!$C$4)^1 | C7: =O7*(Inputs!$B$14+(Scenarios!$C$3-Inputs!$B$14)*MIN(2,5)/5)/(1+Scenarios!$C$4)^2 | D7: =P7*(Inputs!$B$14+(Scenarios!$C$3-Inputs!$B$14)*MIN(3,5)/5)/(1+Scenarios!$C$4)^3 | E7: =Q7*(Inputs!$B$14+(Scenarios!$C$3-Inputs!$B$14)*MIN(4,5)/5)/(1+Scenarios!$C$4)^4 | F7: =R7*(Inputs!$B$14+(Scenarios!$C$3-Inputs!$B$14)*MIN(5,5)/5)/(1+Scenarios!$C$4)^5 | G7: =S7*(Inputs!$B$14+(Scenarios!$C$3-Inputs!$B$14)*MIN(6,5)/5)/(1+Scenarios!$C$4)^6 | H7: =T7*(Inputs!$B$14+(Scenarios!$C$3-Inputs!$B$14)*MIN(7,5)/5)/(1+Scenarios!$C$4)^7 | I7: =U7*(Inputs!$B$14+(Scenarios!$C$3-Inputs!$B$14)*MIN(8,5)/5)/(1+Scenarios!$C$4)^8 | J7: =V7*(Inputs!$B$14+(Scenarios!$C$3-Inputs!$B$14)*MIN(9,5)/5)/(1+Scenarios!$C$4)^9 | K7: =W7*(Inputs!$B$14+(Scenarios!$C$3-Inputs!$B$14)*MIN(10,5)/5)/(1+Scenarios!$C$4)^10 | L7: =W7*(Inputs!$B$14+(Scenarios!$C$3-Inputs!$B$14))*(1+Scenarios!$C$5)/(Scenarios!$C$4-Scenarios!$C$5)/(1+Scenarios!$C$4)^10 | M7: =(SUM(B7:L7)+Inputs!$B$17)*Inputs!$B$8/Inputs!$B$3*Inputs!$B$2 | N7: =Inputs!$B$6*(1+($A7-($A7-Scenarios!$C$5)*(1-1)/9)) | O7: =N7*(1+($A7-($A7-Scenarios!$C$5)*(2-1)/9)) | P7: =O7*(1+($A7-($A7-Scenarios!$C$5)*(3-1)/9)) | Q7: =P7*(1+($A7-($A7-Scenarios!$C$5)*(4-1)/9)) | R7: =Q7*(1+($A7-($A7-Scenarios!$C$5)*(5-1)/9)) | S7: =R7*(1+($A7-($A7-Scenarios!$C$5)*(6-1)/9)) | T7: =S7*(1+($A7-($A7-Scenarios!$C$5)*(7-1)/9)) | U7: =T7*(1+($A7-($A7-Scenarios!$C$5)*(8-1)/9)) | V7: =U7*(1+($A7-($A7-Scenarios!$C$5)*(9-1)/9)) | W7: =V7*(1+($A7-($A7-Scenarios!$C$5)*(10-1)/9))
A8: -0.2 | B8: =N8*(Inputs!$B$14+(Scenarios!$C$3-Inputs!$B$14)*MIN(1,5)/5)/(1+Scenarios!$C$4)^1 | C8: =O8*(Inputs!$B$14+(Scenarios!$C$3-Inputs!$B$14)*MIN(2,5)/5)/(1+Scenarios!$C$4)^2 | D8: =P8*(Inputs!$B$14+(Scenarios!$C$3-Inputs!$B$14)*MIN(3,5)/5)/(1+Scenarios!$C$4)^3 | E8: =Q8*(Inputs!$B$14+(Scenarios!$C$3-Inputs!$B$14)*MIN(4,5)/5)/(1+Scenarios!$C$4)^4 | F8: =R8*(Inputs!$B$14+(Scenarios!$C$3-Inputs!$B$14)*MIN(5,5)/5)/(1+Scenarios!$C$4)^5 | G8: =S8*(Inputs!$B$14+(Scenarios!$C$3-Inputs!$B$14)*MIN(6,5)/5)/(1+Scenarios!$C$4)^6 | H8: =T8*(Inputs!$B$14+(Scenarios!$C$3-Inputs!$B$14)*MIN(7,5)/5)/(1+Scenarios!$C$4)^7 | I8: =U8*(Inputs!$B$14+(Scenarios!$C$3-Inputs!$B$14)*MIN(8,5)/5)/(1+Scenarios!$C$4)^8 | J8: =V8*(Inputs!$B$14+(Scenarios!$C$3-Inputs!$B$14)*MIN(9,5)/5)/(1+Scenarios!$C$4)^9 | K8: =W8*(Inputs!$B$14+(Scenarios!$C$3-Inputs!$B$14)*MIN(10,5)/5)/(1+Scenarios!$C$4)^10 | L8: =W8*(Inputs!$B$14+(Scenarios!$C$3-Inputs!$B$14))*(1+Scenarios!$C$5)/(Scenarios!$C$4-Scenarios!$C$5)/(1+Scenarios!$C$4)^10 | M8: =(SUM(B8:L8)+Inputs!$B$17)*Inputs!$B$8/Inputs!$B$3*Inputs!$B$2 | N8: =Inputs!$B$6*(1+($A8-($A8-Scenarios!$C$5)*(1-1)/9)) | O8: =N8*(1+($A8-($A8-Scenarios!$C$5)*(2-1)/9)) | P8: =O8*(1+($A8-($A8-Scenarios!$C$5)*(3-1)/9)) | Q8: =P8*(1+($A8-($A8-Scenarios!$C$5)*(4-1)/9)) | R8: =Q8*(1+($A8-($A8-Scenarios!$C$5)*(5-1)/9)) | S8: =R8*(1+($A8-($A8-Scenarios!$C$5)*(6-1)/9)) | T8: =S8*(1+($A8-($A8-Scenarios!$C$5)*(7-1)/9)) | U8: =T8*(1+($A8-($A8-Scenarios!$C$5)*(8-1)/9)) | V8: =U8*(1+($A8-($A8-Scenarios!$C$5)*(9-1)/9)) | W8: =V8*(1+($A8-($A8-Scenarios!$C$5)*(10-1)/9))
A9: -0.175 | B9: =N9*(Inputs!$B$14+(Scenarios!$C$3-Inputs!$B$14)*MIN(1,5)/5)/(1+Scenarios!$C$4)^1 | C9: =O9*(Inputs!$B$14+(Scenarios!$C$3-Inputs!$B$14)*MIN(2,5)/5)/(1+Scenarios!$C$4)^2 | D9: =P9*(Inputs!$B$14+(Scenarios!$C$3-Inputs!$B$14)*MIN(3,5)/5)/(1+Scenarios!$C$4)^3 | E9: =Q9*(Inputs!$B$14+(Scenarios!$C$3-Inputs!$B$14)*MIN(4,5)/5)/(1+Scenarios!$C$4)^4 | F9: =R9*(Inputs!$B$14+(Scenarios!$C$3-Inputs!$B$14)*MIN(5,5)/5)/(1+Scenarios!$C$4)^5 | G9: =S9*(Inputs!$B$14+(Scenarios!$C$3-Inputs!$B$14)*MIN(6,5)/5)/(1+Scenarios!$C$4)^6 | H9: =T9*(Inputs!$B$14+(Scenarios!$C$3-Inputs!$B$14)*MIN(7,5)/5)/(1+Scenarios!$C$4)^7 | I9: =U9*(Inputs!$B$14+(Scenarios!$C$3-Inputs!$B$14)*MIN(8,5)/5)/(1+Scenarios!$C$4)^8 | J9: =V9*(Inputs!$B$14+(Scenarios!$C$3-Inputs!$B$14)*MIN(9,5)/5)/(1+Scenarios!$C$4)^9 | K9: =W9*(Inputs!$B$14+(Scenarios!$C$3-Inputs!$B$14)*MIN(10,5)/5)/(1+Scenarios!$C$4)^10 | L9: =W9*(Inputs!$B$14+(Scenarios!$C$3-Inputs!$B$14))*(1+Scenarios!$C$5)/(Scenarios!$C$4-Scenarios!$C$5)/(1+Scenarios!$C$4)^10 | M9: =(SUM(B9:L9)+Inputs!$B$17)*Inputs!$B$8/Inputs!$B$3*Inputs!$B$2 | N9: =Inputs!$B$6*(1+($A9-($A9-Scenarios!$C$5)*(1-1)/9)) | O9: =N9*(1+($A9-($A9-Scenarios!$C$5)*(2-1)/9)) | P9: =O9*(1+($A9-($A9-Scenarios!$C$5)*(3-1)/9)) | Q9: =P9*(1+($A9-($A9-Scenarios!$C$5)*(4-1)/9)) | R9: =Q9*(1+($A9-($A9-Scenarios!$C$5)*(5-1)/9)) | S9: =R9*(1+($A9-($A9-Scenarios!$C$5)*(6-1)/9)) | T9: =S9*(1+($A9-($A9-Scenarios!$C$5)*(7-1)/9)) | U9: =T9*(1+($A9-($A9-Scenarios!$C$5)*(8-1)/9)) | V9: =U9*(1+($A9-($A9-Scenarios!$C$5)*(9-1)/9)) | W9: =V9*(1+($A9-($A9-Scenarios!$C$5)*(10-1)/9))
A10: -0.15 | B10: =N10*(Inputs!$B$14+(Scenarios!$C$3-Inputs!$B$14)*MIN(1,5)/5)/(1+Scenarios!$C$4)^1 | C10: =O10*(Inputs!$B$14+(Scenarios!$C$3-Inputs!$B$14)*MIN(2,5)/5)/(1+Scenarios!$C$4)^2 | D10: =P10*(Inputs!$B$14+(Scenarios!$C$3-Inputs!$B$14)*MIN(3,5)/5)/(1+Scenarios!$C$4)^3 | E10: =Q10*(Inputs!$B$14+(Scenarios!$C$3-Inputs!$B$14)*MIN(4,5)/5)/(1+Scenarios!$C$4)^4 | F10: =R10*(Inputs!$B$14+(Scenarios!$C$3-Inputs!$B$14)*MIN(5,5)/5)/(1+Scenarios!$C$4)^5 | G10: =S10*(Inputs!$B$14+(Scenarios!$C$3-Inputs!$B$14)*MIN(6,5)/5)/(1+Scenarios!$C$4)^6 | H10: =T10*(Inputs!$B$14+(Scenarios!$C$3-Inputs!$B$14)*MIN(7,5)/5)/(1+Scenarios!$C$4)^7 | I10: =U10*(Inputs!$B$14+(Scenarios!$C$3-Inputs!$B$14)*MIN(8,5)/5)/(1+Scenarios!$C$4)^8 | J10: =V10*(Inputs!$B$14+(Scenarios!$C$3-Inputs!$B$14)*MIN(9,5)/5)/(1+Scenarios!$C$4)^9 | K10: =W10*(Inputs!$B$14+(Scenarios!$C$3-Inputs!$B$14)*MIN(10,5)/5)/(1+Scenarios!$C$4)^10 | L10: =W10*(Inputs!$B$14+(Scenarios!$C$3-Inputs!$B$14))*(1+Scenarios!$C$5)/(Scenarios!$C$4-Scenarios!$C$5)/(1+Scenarios!$C$4)^10 | M10: =(SUM(B10:L10)+Inputs!$B$17)*Inputs!$B$8/Inputs!$B$3*Inputs!$B$2 | N10: =Inputs!$B$6*(1+($A10-($A10-Scenarios!$C$5)*(1-1)/9)) | O10: =N10*(1+($A10-($A10-Scenarios!$C$5)*(2-1)/9)) | P10: =O10*(1+($A10-($A10-Scenarios!$C$5)*(3-1)/9)) | Q10: =P10*(1+($A10-($A10-Scenarios!$C$5)*(4-1)/9)) | R10: =Q10*(1+($A10-($A10-Scenarios!$C$5)*(5-1)/9)) | S10: =R10*(1+($A10-($A10-Scenarios!$C$5)*(6-1)/9)) | T10: =S10*(1+($A10-($A10-Scenarios!$C$5)*(7-1)/9)) | U10: =T10*(1+($A10-($A10-Scenarios!$C$5)*(8-1)/9)) | V10: =U10*(1+($A10-($A10-Scenarios!$C$5)*(9-1)/9)) | W10: =V10*(1+($A10-($A10-Scenarios!$C$5)*(10-1)/9))
A11: -0.125 | B11: =N11*(Inputs!$B$14+(Scenarios!$C$3-Inputs!$B$14)*MIN(1,5)/5)/(1+Scenarios!$C$4)^1 | C11: =O11*(Inputs!$B$14+(Scenarios!$C$3-Inputs!$B$14)*MIN(2,5)/5)/(1+Scenarios!$C$4)^2 | D11: =P11*(Inputs!$B$14+(Scenarios!$C$3-Inputs!$B$14)*MIN(3,5)/5)/(1+Scenarios!$C$4)^3 | E11: =Q11*(Inputs!$B$14+(Scenarios!$C$3-Inputs!$B$14)*MIN(4,5)/5)/(1+Scenarios!$C$4)^4 | F11: =R11*(Inputs!$B$14+(Scenarios!$C$3-Inputs!$B$14)*MIN(5,5)/5)/(1+Scenarios!$C$4)^5 | G11: =S11*(Inputs!$B$14+(Scenarios!$C$3-Inputs!$B$14)*MIN(6,5)/5)/(1+Scenarios!$C$4)^6 | H11: =T11*(Inputs!$B$14+(Scenarios!$C$3-Inputs!$B$14)*MIN(7,5)/5)/(1+Scenarios!$C$4)^7 | I11: =U11*(Inputs!$B$14+(Scenarios!$C$3-Inputs!$B$14)*MIN(8,5)/5)/(1+Scenarios!$C$4)^8 | J11: =V11*(Inputs!$B$14+(Scenarios!$C$3-Inputs!$B$14)*MIN(9,5)/5)/(1+Scenarios!$C$4)^9 | K11: =W11*(Inputs!$B$14+(Scenarios!$C$3-Inputs!$B$14)*MIN(10,5)/5)/(1+Scenarios!$C$4)^10 | L11: =W11*(Inputs!$B$14+(Scenarios!$C$3-Inputs!$B$14))*(1+Scenarios!$C$5)/(Scenarios!$C$4-Scenarios!$C$5)/(1+Scenarios!$C$4)^10 | M11: =(SUM(B11:L11)+Inputs!$B$17)*Inputs!$B$8/Inputs!$B$3*Inputs!$B$2 | N11: =Inputs!$B$6*(1+($A11-($A11-Scenarios!$C$5)*(1-1)/9)) | O11: =N11*(1+($A11-($A11-Scenarios!$C$5)*(2-1)/9)) | P11: =O11*(1+($A11-($A11-Scenarios!$C$5)*(3-1)/9)) | Q11: =P11*(1+($A11-($A11-Scenarios!$C$5)*(4-1)/9)) | R11: =Q11*(1+($A11-($A11-Scenarios!$C$5)*(5-1)/9)) | S11: =R11*(1+($A11-($A11-Scenarios!$C$5)*(6-1)/9)) | T11: =S11*(1+($A11-($A11-Scenarios!$C$5)*(7-1)/9)) | U11: =T11*(1+($A11-($A11-Scenarios!$C$5)*(8-1)/9)) | V11: =U11*(1+($A11-($A11-Scenarios!$C$5)*(9-1)/9)) | W11: =V11*(1+($A11-($A11-Scenarios!$C$5)*(10-1)/9))
A12: -0.1 | B12: =N12*(Inputs!$B$14+(Scenarios!$C$3-Inputs!$B$14)*MIN(1,5)/5)/(1+Scenarios!$C$4)^1 | C12: =O12*(Inputs!$B$14+(Scenarios!$C$3-Inputs!$B$14)*MIN(2,5)/5)/(1+Scenarios!$C$4)^2 | D12: =P12*(Inputs!$B$14+(Scenarios!$C$3-Inputs!$B$14)*MIN(3,5)/5)/(1+Scenarios!$C$4)^3 | E12: =Q12*(Inputs!$B$14+(Scenarios!$C$3-Inputs!$B$14)*MIN(4,5)/5)/(1+Scenarios!$C$4)^4 | F12: =R12*(Inputs!$B$14+(Scenarios!$C$3-Inputs!$B$14)*MIN(5,5)/5)/(1+Scenarios!$C$4)^5 | G12: =S12*(Inputs!$B$14+(Scenarios!$C$3-Inputs!$B$14)*MIN(6,5)/5)/(1+Scenarios!$C$4)^6 | H12: =T12*(Inputs!$B$14+(Scenarios!$C$3-Inputs!$B$14)*MIN(7,5)/5)/(1+Scenarios!$C$4)^7 | I12: =U12*(Inputs!$B$14+(Scenarios!$C$3-Inputs!$B$14)*MIN(8,5)/5)/(1+Scenarios!$C$4)^8 | J12: =V12*(Inputs!$B$14+(Scenarios!$C$3-Inputs!$B$14)*MIN(9,5)/5)/(1+Scenarios!$C$4)^9 | K12: =W12*(Inputs!$B$14+(Scenarios!$C$3-Inputs!$B$14)*MIN(10,5)/5)/(1+Scenarios!$C$4)^10 | L12: =W12*(Inputs!$B$14+(Scenarios!$C$3-Inputs!$B$14))*(1+Scenarios!$C$5)/(Scenarios!$C$4-Scenarios!$C$5)/(1+Scenarios!$C$4)^10 | M12: =(SUM(B12:L12)+Inputs!$B$17)*Inputs!$B$8/Inputs!$B$3*Inputs!$B$2 | N12: =Inputs!$B$6*(1+($A12-($A12-Scenarios!$C$5)*(1-1)/9)) | O12: =N12*(1+($A12-($A12-Scenarios!$C$5)*(2-1)/9)) | P12: =O12*(1+($A12-($A12-Scenarios!$C$5)*(3-1)/9)) | Q12: =P12*(1+($A12-($A12-Scenarios!$C$5)*(4-1)/9)) | R12: =Q12*(1+($A12-($A12-Scenarios!$C$5)*(5-1)/9)) | S12: =R12*(1+($A12-($A12-Scenarios!$C$5)*(6-1)/9)) | T12: =S12*(1+($A12-($A12-Scenarios!$C$5)*(7-1)/9)) | U12: =T12*(1+($A12-($A12-Scenarios!$C$5)*(8-1)/9)) | V12: =U12*(1+($A12-($A12-Scenarios!$C$5)*(9-1)/9)) | W12: =V12*(1+($A12-($A12-Scenarios!$C$5)*(10-1)/9))
A13: -0.075 | B13: =N13*(Inputs!$B$14+(Scenarios!$C$3-Inputs!$B$14)*MIN(1,5)/5)/(1+Scenarios!$C$4)^1 | C13: =O13*(Inputs!$B$14+(Scenarios!$C$3-Inputs!$B$14)*MIN(2,5)/5)/(1+Scenarios!$C$4)^2 | D13: =P13*(Inputs!$B$14+(Scenarios!$C$3-Inputs!$B$14)*MIN(3,5)/5)/(1+Scenarios!$C$4)^3 | E13: =Q13*(Inputs!$B$14+(Scenarios!$C$3-Inputs!$B$14)*MIN(4,5)/5)/(1+Scenarios!$C$4)^4 | F13: =R13*(Inputs!$B$14+(Scenarios!$C$3-Inputs!$B$14)*MIN(5,5)/5)/(1+Scenarios!$C$4)^5 | G13: =S13*(Inputs!$B$14+(Scenarios!$C$3-Inputs!$B$14)*MIN(6,5)/5)/(1+Scenarios!$C$4)^6 | H13: =T13*(Inputs!$B$14+(Scenarios!$C$3-Inputs!$B$14)*MIN(7,5)/5)/(1+Scenarios!$C$4)^7 | I13: =U13*(Inputs!$B$14+(Scenarios!$C$3-Inputs!$B$14)*MIN(8,5)/5)/(1+Scenarios!$C$4)^8 | J13: =V13*(Inputs!$B$14+(Scenarios!$C$3-Inputs!$B$14)*MIN(9,5)/5)/(1+Scenarios!$C$4)^9 | K13: =W13*(Inputs!$B$14+(Scenarios!$C$3-Inputs!$B$14)*MIN(10,5)/5)/(1+Scenarios!$C$4)^10 | L13: =W13*(Inputs!$B$14+(Scenarios!$C$3-Inputs!$B$14))*(1+Scenarios!$C$5)/(Scenarios!$C$4-Scenarios!$C$5)/(1+Scenarios!$C$4)^10 | M13: =(SUM(B13:L13)+Inputs!$B$17)*Inputs!$B$8/Inputs!$B$3*Inputs!$B$2 | N13: =Inputs!$B$6*(1+($A13-($A13-Scenarios!$C$5)*(1-1)/9)) | O13: =N13*(1+($A13-($A13-Scenarios!$C$5)*(2-1)/9)) | P13: =O13*(1+($A13-($A13-Scenarios!$C$5)*(3-1)/9)) | Q13: =P13*(1+($A13-($A13-Scenarios!$C$5)*(4-1)/9)) | R13: =Q13*(1+($A13-($A13-Scenarios!$C$5)*(5-1)/9)) | S13: =R13*(1+($A13-($A13-Scenarios!$C$5)*(6-1)/9)) | T13: =S13*(1+($A13-($A13-Scenarios!$C$5)*(7-1)/9)) | U13: =T13*(1+($A13-($A13-Scenarios!$C$5)*(8-1)/9)) | V13: =U13*(1+($A13-($A13-Scenarios!$C$5)*(9-1)/9)) | W13: =V13*(1+($A13-($A13-Scenarios!$C$5)*(10-1)/9))
A14: -0.05 | B14: =N14*(Inputs!$B$14+(Scenarios!$C$3-Inputs!$B$14)*MIN(1,5)/5)/(1+Scenarios!$C$4)^1 | C14: =O14*(Inputs!$B$14+(Scenarios!$C$3-Inputs!$B$14)*MIN(2,5)/5)/(1+Scenarios!$C$4)^2 | D14: =P14*(Inputs!$B$14+(Scenarios!$C$3-Inputs!$B$14)*MIN(3,5)/5)/(1+Scenarios!$C$4)^3 | E14: =Q14*(Inputs!$B$14+(Scenarios!$C$3-Inputs!$B$14)*MIN(4,5)/5)/(1+Scenarios!$C$4)^4 | F14: =R14*(Inputs!$B$14+(Scenarios!$C$3-Inputs!$B$14)*MIN(5,5)/5)/(1+Scenarios!$C$4)^5 | G14: =S14*(Inputs!$B$14+(Scenarios!$C$3-Inputs!$B$14)*MIN(6,5)/5)/(1+Scenarios!$C$4)^6 | H14: =T14*(Inputs!$B$14+(Scenarios!$C$3-Inputs!$B$14)*MIN(7,5)/5)/(1+Scenarios!$C$4)^7 | I14: =U14*(Inputs!$B$14+(Scenarios!$C$3-Inputs!$B$14)*MIN(8,5)/5)/(1+Scenarios!$C$4)^8 | J14: =V14*(Inputs!$B$14+(Scenarios!$C$3-Inputs!$B$14)*MIN(9,5)/5)/(1+Scenarios!$C$4)^9 | K14: =W14*(Inputs!$B$14+(Scenarios!$C$3-Inputs!$B$14)*MIN(10,5)/5)/(1+Scenarios!$C$4)^10 | L14: =W14*(Inputs!$B$14+(Scenarios!$C$3-Inputs!$B$14))*(1+Scenarios!$C$5)/(Scenarios!$C$4-Scenarios!$C$5)/(1+Scenarios!$C$4)^10 | M14: =(SUM(B14:L14)+Inputs!$B$17)*Inputs!$B$8/Inputs!$B$3*Inputs!$B$2 | N14: =Inputs!$B$6*(1+($A14-($A14-Scenarios!$C$5)*(1-1)/9)) | O14: =N14*(1+($A14-($A14-Scenarios!$C$5)*(2-1)/9)) | P14: =O14*(1+($A14-($A14-Scenarios!$C$5)*(3-1)/9)) | Q14: =P14*(1+($A14-($A14-Scenarios!$C$5)*(4-1)/9)) | R14: =Q14*(1+($A14-($A14-Scenarios!$C$5)*(5-1)/9)) | S14: =R14*(1+($A14-($A14-Scenarios!$C$5)*(6-1)/9)) | T14: =S14*(1+($A14-($A14-Scenarios!$C$5)*(7-1)/9)) | U14: =T14*(1+($A14-($A14-Scenarios!$C$5)*(8-1)/9)) | V14: =U14*(1+($A14-($A14-Scenarios!$C$5)*(9-1)/9)) | W14: =V14*(1+($A14-($A14-Scenarios!$C$5)*(10-1)/9))
A15: -0.025 | B15: =N15*(Inputs!$B$14+(Scenarios!$C$3-Inputs!$B$14)*MIN(1,5)/5)/(1+Scenarios!$C$4)^1 | C15: =O15*(Inputs!$B$14+(Scenarios!$C$3-Inputs!$B$14)*MIN(2,5)/5)/(1+Scenarios!$C$4)^2 | D15: =P15*(Inputs!$B$14+(Scenarios!$C$3-Inputs!$B$14)*MIN(3,5)/5)/(1+Scenarios!$C$4)^3 | E15: =Q15*(Inputs!$B$14+(Scenarios!$C$3-Inputs!$B$14)*MIN(4,5)/5)/(1+Scenarios!$C$4)^4 | F15: =R15*(Inputs!$B$14+(Scenarios!$C$3-Inputs!$B$14)*MIN(5,5)/5)/(1+Scenarios!$C$4)^5 | G15: =S15*(Inputs!$B$14+(Scenarios!$C$3-Inputs!$B$14)*MIN(6,5)/5)/(1+Scenarios!$C$4)^6 | H15: =T15*(Inputs!$B$14+(Scenarios!$C$3-Inputs!$B$14)*MIN(7,5)/5)/(1+Scenarios!$C$4)^7 | I15: =U15*(Inputs!$B$14+(Scenarios!$C$3-Inputs!$B$14)*MIN(8,5)/5)/(1+Scenarios!$C$4)^8 | J15: =V15*(Inputs!$B$14+(Scenarios!$C$3-Inputs!$B$14)*MIN(9,5)/5)/(1+Scenarios!$C$4)^9 | K15: =W15*(Inputs!$B$14+(Scenarios!$C$3-Inputs!$B$14)*MIN(10,5)/5)/(1+Scenarios!$C$4)^10 | L15: =W15*(Inputs!$B$14+(Scenarios!$C$3-Inputs!$B$14))*(1+Scenarios!$C$5)/(Scenarios!$C$4-Scenarios!$C$5)/(1+Scenarios!$C$4)^10 | M15: =(SUM(B15:L15)+Inputs!$B$17)*Inputs!$B$8/Inputs!$B$3*Inputs!$B$2 | N15: =Inputs!$B$6*(1+($A15-($A15-Scenarios!$C$5)*(1-1)/9)) | O15: =N15*(1+($A15-($A15-Scenarios!$C$5)*(2-1)/9)) | P15: =O15*(1+($A15-($A15-Scenarios!$C$5)*(3-1)/9)) | Q15: =P15*(1+($A15-($A15-Scenarios!$C$5)*(4-1)/9)) | R15: =Q15*(1+($A15-($A15-Scenarios!$C$5)*(5-1)/9)) | S15: =R15*(1+($A15-($A15-Scenarios!$C$5)*(6-1)/9)) | T15: =S15*(1+($A15-($A15-Scenarios!$C$5)*(7-1)/9)) | U15: =T15*(1+($A15-($A15-Scenarios!$C$5)*(8-1)/9)) | V15: =U15*(1+($A15-($A15-Scenarios!$C$5)*(9-1)/9)) | W15: =V15*(1+($A15-($A15-Scenarios!$C$5)*(10-1)/9))
... A96: 2 | B96: =N96*(Inputs!$B$14+(Scenarios!$C$3-Inputs!$B$14)*MIN(1,5)/5)/(1+Scenarios!$C$4)^1 | C96: =O96*(Inputs!$B$14+(Scenarios!$C$3-Inputs!$B$14)*MIN(2,5)/5)/(1+Scenarios!$C$4)^2 | D96: =P96*(Inputs!$B$14+(Scenarios!$C$3-Inputs!$B$14)*MIN(3,5)/5)/(1+Scenarios!$C$4)^3 | E96: =Q96*(Inputs!$B$14+(Scenarios!$C$3-Inputs!$B$14)*MIN(4,5)/5)/(1+Scenarios!$C$4)^4 | F96: =R96*(Inputs!$B$14+(Scenarios!$C$3-Inputs!$B$14)*MIN(5,5)/5)/(1+Scenarios!$C$4)^5 | G96: =S96*(Inputs!$B$14+(Scenarios!$C$3-Inputs!$B$14)*MIN(6,5)/5)/(1+Scenarios!$C$4)^6 | H96: =T96*(Inputs!$B$14+(Scenarios!$C$3-Inputs!$B$14)*MIN(7,5)/5)/(1+Scenarios!$C$4)^7 | I96: =U96*(Inputs!$B$14+(Scenarios!$C$3-Inputs!$B$14)*MIN(8,5)/5)/(1+Scenarios!$C$4)^8 | J96: =V96*(Inputs!$B$14+(Scenarios!$C$3-Inputs!$B$14)*MIN(9,5)/5)/(1+Scenarios!$C$4)^9 | K96: =W96*(Inputs!$B$14+(Scenarios!$C$3-Inputs!$B$14)*MIN(10,5)/5)/(1+Scenarios!$C$4)^10 | L96: =W96*(Inputs!$B$14+(Scenarios!$C$3-Inputs!$B$14))*(1+Scenarios!$C$5)/(Scenarios!$C$4-Scenarios!$C$5)/(1+Scenarios!$C$4)^10 | M96: =(SUM(B96:L96)+Inputs!$B$17)*Inputs!$B$8/Inputs!$B$3*Inputs!$B$2 | N96: =Inputs!$B$6*(1+($A96-($A96-Scenarios!$C$5)*(1-1)/9)) | O96: =N96*(1+($A96-($A96-Scenarios!$C$5)*(2-1)/9)) | P96: =O96*(1+($A96-($A96-Scenarios!$C$5)*(3-1)/9)) | Q96: =P96*(1+($A96-($A96-Scenarios!$C$5)*(4-1)/9)) | R96: =Q96*(1+($A96-($A96-Scenarios!$C$5)*(5-1)/9)) | S96: =R96*(1+($A96-($A96-Scenarios!$C$5)*(6-1)/9)) | T96: =S96*(1+($A96-($A96-Scenarios!$C$5)*(7-1)/9)) | U96: =T96*(1+($A96-($A96-Scenarios!$C$5)*(8-1)/9)) | V96: =U96*(1+($A96-($A96-Scenarios!$C$5)*(9-1)/9)) | W96: =V96*(1+($A96-($A96-Scenarios!$C$5)*(10-1)/9))

Sheet Sensitivity
A1: Base-case value/share: WACC (rows) × terminal g (cols). Uses Base FCF path in DCF!B10:K10.
A3: WACC \ g | B3: 0.02 | C3: 0.025 | D3: 0.03 | E3: 0.035 | F3: 0.04
A4: =Scenarios!$C$4+(-0.02) | B4: =(SUMPRODUCT(DCF!$B$20:$K$20,1/(1+$A4)^DCF!$B$16:$K$16)+DCF!$K$20*(1+B$3)/($A4-B$3)/(1+$A4)^10+Inputs!$B$17)*Inputs!$B$8/Inputs!$B$3*Inputs!$B$2 | C4: =(SUMPRODUCT(DCF!$B$20:$K$20,1/(1+$A4)^DCF!$B$16:$K$16)+DCF!$K$20*(1+C$3)/($A4-C$3)/(1+$A4)^10+Inputs!$B$17)*Inputs!$B$8/Inputs!$B$3*Inputs!$B$2 | D4: =(SUMPRODUCT(DCF!$B$20:$K$20,1/(1+$A4)^DCF!$B$16:$K$16)+DCF!$K$20*(1+D$3)/($A4-D$3)/(1+$A4)^10+Inputs!$B$17)*Inputs!$B$8/Inputs!$B$3*Inputs!$B$2 | E4: =(SUMPRODUCT(DCF!$B$20:$K$20,1/(1+$A4)^DCF!$B$16:$K$16)+DCF!$K$20*(1+E$3)/($A4-E$3)/(1+$A4)^10+Inputs!$B$17)*Inputs!$B$8/Inputs!$B$3*Inputs!$B$2 | F4: =(SUMPRODUCT(DCF!$B$20:$K$20,1/(1+$A4)^DCF!$B$16:$K$16)+DCF!$K$20*(1+F$3)/($A4-F$3)/(1+$A4)^10+Inputs!$B$17)*Inputs!$B$8/Inputs!$B$3*Inputs!$B$2
A5: =Scenarios!$C$4+(-0.01) | B5: =(SUMPRODUCT(DCF!$B$20:$K$20,1/(1+$A5)^DCF!$B$16:$K$16)+DCF!$K$20*(1+B$3)/($A5-B$3)/(1+$A5)^10+Inputs!$B$17)*Inputs!$B$8/Inputs!$B$3*Inputs!$B$2 | C5: =(SUMPRODUCT(DCF!$B$20:$K$20,1/(1+$A5)^DCF!$B$16:$K$16)+DCF!$K$20*(1+C$3)/($A5-C$3)/(1+$A5)^10+Inputs!$B$17)*Inputs!$B$8/Inputs!$B$3*Inputs!$B$2 | D5: =(SUMPRODUCT(DCF!$B$20:$K$20,1/(1+$A5)^DCF!$B$16:$K$16)+DCF!$K$20*(1+D$3)/($A5-D$3)/(1+$A5)^10+Inputs!$B$17)*Inputs!$B$8/Inputs!$B$3*Inputs!$B$2 | E5: =(SUMPRODUCT(DCF!$B$20:$K$20,1/(1+$A5)^DCF!$B$16:$K$16)+DCF!$K$20*(1+E$3)/($A5-E$3)/(1+$A5)^10+Inputs!$B$17)*Inputs!$B$8/Inputs!$B$3*Inputs!$B$2 | F5: =(SUMPRODUCT(DCF!$B$20:$K$20,1/(1+$A5)^DCF!$B$16:$K$16)+DCF!$K$20*(1+F$3)/($A5-F$3)/(1+$A5)^10+Inputs!$B$17)*Inputs!$B$8/Inputs!$B$3*Inputs!$B$2
A6: =Scenarios!$C$4+(0) | B6: =(SUMPRODUCT(DCF!$B$20:$K$20,1/(1+$A6)^DCF!$B$16:$K$16)+DCF!$K$20*(1+B$3)/($A6-B$3)/(1+$A6)^10+Inputs!$B$17)*Inputs!$B$8/Inputs!$B$3*Inputs!$B$2 | C6: =(SUMPRODUCT(DCF!$B$20:$K$20,1/(1+$A6)^DCF!$B$16:$K$16)+DCF!$K$20*(1+C$3)/($A6-C$3)/(1+$A6)^10+Inputs!$B$17)*Inputs!$B$8/Inputs!$B$3*Inputs!$B$2 | D6: =(SUMPRODUCT(DCF!$B$20:$K$20,1/(1+$A6)^DCF!$B$16:$K$16)+DCF!$K$20*(1+D$3)/($A6-D$3)/(1+$A6)^10+Inputs!$B$17)*Inputs!$B$8/Inputs!$B$3*Inputs!$B$2 | E6: =(SUMPRODUCT(DCF!$B$20:$K$20,1/(1+$A6)^DCF!$B$16:$K$16)+DCF!$K$20*(1+E$3)/($A6-E$3)/(1+$A6)^10+Inputs!$B$17)*Inputs!$B$8/Inputs!$B$3*Inputs!$B$2 | F6: =(SUMPRODUCT(DCF!$B$20:$K$20,1/(1+$A6)^DCF!$B$16:$K$16)+DCF!$K$20*(1+F$3)/($A6-F$3)/(1+$A6)^10+Inputs!$B$17)*Inputs!$B$8/Inputs!$B$3*Inputs!$B$2
A7: =Scenarios!$C$4+(0.01) | B7: =(SUMPRODUCT(DCF!$B$20:$K$20,1/(1+$A7)^DCF!$B$16:$K$16)+DCF!$K$20*(1+B$3)/($A7-B$3)/(1+$A7)^10+Inputs!$B$17)*Inputs!$B$8/Inputs!$B$3*Inputs!$B$2 | C7: =(SUMPRODUCT(DCF!$B$20:$K$20,1/(1+$A7)^DCF!$B$16:$K$16)+DCF!$K$20*(1+C$3)/($A7-C$3)/(1+$A7)^10+Inputs!$B$17)*Inputs!$B$8/Inputs!$B$3*Inputs!$B$2 | D7: =(SUMPRODUCT(DCF!$B$20:$K$20,1/(1+$A7)^DCF!$B$16:$K$16)+DCF!$K$20*(1+D$3)/($A7-D$3)/(1+$A7)^10+Inputs!$B$17)*Inputs!$B$8/Inputs!$B$3*Inputs!$B$2 | E7: =(SUMPRODUCT(DCF!$B$20:$K$20,1/(1+$A7)^DCF!$B$16:$K$16)+DCF!$K$20*(1+E$3)/($A7-E$3)/(1+$A7)^10+Inputs!$B$17)*Inputs!$B$8/Inputs!$B$3*Inputs!$B$2 | F7: =(SUMPRODUCT(DCF!$B$20:$K$20,1/(1+$A7)^DCF!$B$16:$K$16)+DCF!$K$20*(1+F$3)/($A7-F$3)/(1+$A7)^10+Inputs!$B$17)*Inputs!$B$8/Inputs!$B$3*Inputs!$B$2
A8: =Scenarios!$C$4+(0.02) | B8: =(SUMPRODUCT(DCF!$B$20:$K$20,1/(1+$A8)^DCF!$B$16:$K$16)+DCF!$K$20*(1+B$3)/($A8-B$3)/(1+$A8)^10+Inputs!$B$17)*Inputs!$B$8/Inputs!$B$3*Inputs!$B$2 | C8: =(SUMPRODUCT(DCF!$B$20:$K$20,1/(1+$A8)^DCF!$B$16:$K$16)+DCF!$K$20*(1+C$3)/($A8-C$3)/(1+$A8)^10+Inputs!$B$17)*Inputs!$B$8/Inputs!$B$3*Inputs!$B$2 | D8: =(SUMPRODUCT(DCF!$B$20:$K$20,1/(1+$A8)^DCF!$B$16:$K$16)+DCF!$K$20*(1+D$3)/($A8-D$3)/(1+$A8)^10+Inputs!$B$17)*Inputs!$B$8/Inputs!$B$3*Inputs!$B$2 | E8: =(SUMPRODUCT(DCF!$B$20:$K$20,1/(1+$A8)^DCF!$B$16:$K$16)+DCF!$K$20*(1+E$3)/($A8-E$3)/(1+$A8)^10+Inputs!$B$17)*Inputs!$B$8/Inputs!$B$3*Inputs!$B$2 | F8: =(SUMPRODUCT(DCF!$B$20:$K$20,1/(1+$A8)^DCF!$B$16:$K$16)+DCF!$K$20*(1+F$3)/($A8-F$3)/(1+$A8)^10+Inputs!$B$17)*Inputs!$B$8/Inputs!$B$3*Inputs!$B$2
A11: Base value/share: Y1 growth multiplier (rows) × long-run margin (cols) — approximate via scaling

Sheet Horizons
A1: 2/4/6/8-quarter price-reasonableness check｜2/4/6/8季度股价合理性检验. Price_h = (NTM FCF at h × exit multiple + net cash) → per share; PV discounted at scenario WACC.
A3: Quarters | B3: Scenario | C3: Exit EV/FCF | D3: Revenue at h | E3: FCF margin at h | F3: NTM FCF at h | G3: Price at h | H3: PV today | I3: vs price | J3: Implied EV/NTM-FCF at current price
A4: 2 | B4: Bear | C4: 15 | D4: =Inputs!$B$6*(1+Scenarios!B2)^(A4/4) | E4: =Inputs!$B$14+(Scenarios!B3-Inputs!$B$14)*MIN(A4/4+1,5)/5 | F4: =D4*(1+Scenarios!B2)*E4 | G4: =(F4*C4+Inputs!$B$17)*Inputs!$B$8/Inputs!$B$3*Inputs!$B$2 | H4: =G4/(1+Scenarios!B4)^(A4/4) | I4: =H4/Inputs!$B$2-1
A5: 2 | B5: Base | C5: 25 | D5: =Inputs!$B$6*(1+Scenarios!C2)^(A5/4) | E5: =Inputs!$B$14+(Scenarios!C3-Inputs!$B$14)*MIN(A5/4+1,5)/5 | F5: =D5*(1+Scenarios!C2)*E5 | G5: =(F5*C5+Inputs!$B$17)*Inputs!$B$8/Inputs!$B$3*Inputs!$B$2 | H5: =G5/(1+Scenarios!C4)^(A5/4) | I5: =H5/Inputs!$B$2-1 | J5: =IF(F5>0,Inputs!$B$18/F5,"n/m (neg FCF)")
A6: 2 | B6: Bull | C6: 35 | D6: =Inputs!$B$6*(1+Scenarios!D2)^(A6/4) | E6: =Inputs!$B$14+(Scenarios!D3-Inputs!$B$14)*MIN(A6/4+1,5)/5 | F6: =D6*(1+Scenarios!D2)*E6 | G6: =(F6*C6+Inputs!$B$17)*Inputs!$B$8/Inputs!$B$3*Inputs!$B$2 | H6: =G6/(1+Scenarios!D4)^(A6/4) | I6: =H6/Inputs!$B$2-1
A7: 4 | B7: Bear | C7: 15 | D7: =Inputs!$B$6*(1+Scenarios!B2)^(A7/4) | E7: =Inputs!$B$14+(Scenarios!B3-Inputs!$B$14)*MIN(A7/4+1,5)/5 | F7: =D7*(1+Scenarios!B2)*E7 | G7: =(F7*C7+Inputs!$B$17)*Inputs!$B$8/Inputs!$B$3*Inputs!$B$2 | H7: =G7/(1+Scenarios!B4)^(A7/4) | I7: =H7/Inputs!$B$2-1
A8: 4 | B8: Base | C8: 25 | D8: =Inputs!$B$6*(1+Scenarios!C2)^(A8/4) | E8: =Inputs!$B$14+(Scenarios!C3-Inputs!$B$14)*MIN(A8/4+1,5)/5 | F8: =D8*(1+Scenarios!C2)*E8 | G8: =(F8*C8+Inputs!$B$17)*Inputs!$B$8/Inputs!$B$3*Inputs!$B$2 | H8: =G8/(1+Scenarios!C4)^(A8/4) | I8: =H8/Inputs!$B$2-1 | J8: =IF(F8>0,Inputs!$B$18/F8,"n/m (neg FCF)")
A9: 4 | B9: Bull | C9: 35 | D9: =Inputs!$B$6*(1+Scenarios!D2)^(A9/4) | E9: =Inputs!$B$14+(Scenarios!D3-Inputs!$B$14)*MIN(A9/4+1,5)/5 | F9: =D9*(1+Scenarios!D2)*E9 | G9: =(F9*C9+Inputs!$B$17)*Inputs!$B$8/Inputs!$B$3*Inputs!$B$2 | H9: =G9/(1+Scenarios!D4)^(A9/4) | I9: =H9/Inputs!$B$2-1
A10: 6 | B10: Bear | C10: 15 | D10: =Inputs!$B$6*(1+Scenarios!B2)^(A10/4) | E10: =Inputs!$B$14+(Scenarios!B3-Inputs!$B$14)*MIN(A10/4+1,5)/5 | F10: =D10*(1+Scenarios!B2)*E10 | G10: =(F10*C10+Inputs!$B$17)*Inputs!$B$8/Inputs!$B$3*Inputs!$B$2 | H10: =G10/(1+Scenarios!B4)^(A10/4) | I10: =H10/Inputs!$B$2-1
A11: 6 | B11: Base | C11: 25 | D11: =Inputs!$B$6*(1+Scenarios!C2)^(A11/4) | E11: =Inputs!$B$14+(Scenarios!C3-Inputs!$B$14)*MIN(A11/4+1,5)/5 | F11: =D11*(1+Scenarios!C2)*E11 | G11: =(F11*C11+Inputs!$B$17)*Inputs!$B$8/Inputs!$B$3*Inputs!$B$2 | H11: =G11/(1+Scenarios!C4)^(A11/4) | I11: =H11/Inputs!$B$2-1 | J11: =IF(F11>0,Inputs!$B$18/F11,"n/m (neg FCF)")
A12: 6 | B12: Bull | C12: 35 | D12: =Inputs!$B$6*(1+Scenarios!D2)^(A12/4) | E12: =Inputs!$B$14+(Scenarios!D3-Inputs!$B$14)*MIN(A12/4+1,5)/5 | F12: =D12*(1+Scenarios!D2)*E12 | G12: =(F12*C12+Inputs!$B$17)*Inputs!$B$8/Inputs!$B$3*Inputs!$B$2 | H12: =G12/(1+Scenarios!D4)^(A12/4) | I12: =H12/Inputs!$B$2-1
A13: 8 | B13: Bear | C13: 15 | D13: =Inputs!$B$6*(1+Scenarios!B2)^(A13/4) | E13: =Inputs!$B$14+(Scenarios!B3-Inputs!$B$14)*MIN(A13/4+1,5)/5 | F13: =D13*(1+Scenarios!B2)*E13 | G13: =(F13*C13+Inputs!$B$17)*Inputs!$B$8/Inputs!$B$3*Inputs!$B$2 | H13: =G13/(1+Scenarios!B4)^(A13/4) | I13: =H13/Inputs!$B$2-1
A14: 8 | B14: Base | C14: 25 | D14: =Inputs!$B$6*(1+Scenarios!C2)^(A14/4) | E14: =Inputs!$B$14+(Scenarios!C3-Inputs!$B$14)*MIN(A14/4+1,5)/5 | F14: =D14*(1+Scenarios!C2)*E14 | G14: =(F14*C14+Inputs!$B$17)*Inputs!$B$8/Inputs!$B$3*Inputs!$B$2 | H14: =G14/(1+Scenarios!C4)^(A14/4) | I14: =H14/Inputs!$B$2-1 | J14: =IF(F14>0,Inputs!$B$18/F14,"n/m (neg FCF)")
A15: 8 | B15: Bull | C15: 35 | D15: =Inputs!$B$6*(1+Scenarios!D2)^(A15/4) | E15: =Inputs!$B$14+(Scenarios!D3-Inputs!$B$14)*MIN(A15/4+1,5)/5 | F15: =D15*(1+Scenarios!D2)*E15 | G15: =(F15*C15+Inputs!$B$17)*Inputs!$B$8/Inputs!$B$3*Inputs!$B$2 | H15: =G15/(1+Scenarios!D4)^(A15/4) | I15: =H15/Inputs!$B$2-1

Sheet SOTP
A1: Segment 分部 | B1: Revenue (fin cur) INPUT | C1: EV/Sales multiple ASSUMPTION | D1: Segment EV | E1: Note
A2: Subscription 订阅 | D2: =IF(AND(ISNUMBER(B2),ISNUMBER(C2)),B2*C2,0) | E2: INPUT REQUIRED: segment revenue from latest 10-K/10-Q segment note (not auto-fed; left blank to avoid fabrication)
A3: Professional services 专业服务 | D3: =IF(AND(ISNUMBER(B3),ISNUMBER(C3)),B3*C3,0) | E3: INPUT REQUIRED: segment revenue from latest 10-K/10-Q segment note (not auto-fed; left blank to avoid fabrication)
A4: Total EV | D4: =SUM(D2:D3)
A5: Equity value | D5: =D4+Inputs!B17
A6: Value/share USD | D6: =D5*Inputs!B8/Inputs!B3*Inputs!B2

Sheet Comps
A1: Ticker | B1: MarketCap | C1: EV | D1: EV/Revenue | E1: Fwd P/E | F1: Rev growth (yoy) | G1: Gross margin | H1: FCF yield
A2: PANW | B2: 330332930048 | C2: 329828925440 | D2: 28.731 | E2: 82.76782 | F2: 0.345 | G2: 0.70383 | H2: 0.012837427
A3: ZS | B3: 36814491648 | C3: 35208323072 | D3: 10.502 | E3: 40.15037 | F3: 0.249 | G3: 0.76872003 | H3: 0.029198171
A4: S | B4: 8930939904 | C4: 8275692544 | D4: 7.532 | E4: 55.672474 | F4: 0.206 | G4: 0.72540003 | H4: 0.033241814
A5: PLTR | B5: 502239199232 | C5: 493152206848 | D5: 80.11 | E5: 88.87792 | F5: 0.928 | G5: 0.84796 | H5: 0.0042989566
A6: Peer median (ex-subject) | D6: =MEDIAN(D3:D5) | E6: =MEDIAN(E3:E5) | F6: =MEDIAN(F3:F5) | G6: =MEDIAN(G3:G5) | H6: =MEDIAN(H3:H5)
A8: Source: Yahoo Finance info fields (enterpriseToRevenue, forwardPE, revenueGrowth, grossMargins, freeCashflow/marketCap), fetched 2026-10-13 18:12

Sheet ROIC_WACC
A1: EBIT TTM (fin cur) | B1: 104214000
A2: Tax rate | B2: =Inputs!B12
A3: NOPAT | B3: =B1*(1-B2)
A4: Equity (book) | B4: 5101724000
A5: Debt | B5: =Inputs!B5
A6: Cash | B6: =Inputs!B4
A7: Invested capital | B7: =B4+B5-B6
A8: ROIC | B8: =IF(B7>0,B3/B7,"n/m")
A9: Cost of equity (CAPM) | B9: =Inputs!B9+Inputs!B10*Inputs!B11
A10: WACC (equity-weighted approx.) | B10: =Inputs!B16
A11: ROIC − WACC spread | B11: =IF(ISNUMBER(B8),B8-B10,"n/m")
A13: Note: WACC uses CAPM cost of equity (debt weight ignored for simplicity; conservative for low-leverage names). ASSUMPTION.

Sheet History
A1: Quarter | B1: Revenue | C1: Gross Profit | D1: Operating Income | E1: Net Income | F1: Op Cash Flow | G1: CapEx | H1: FCF | I1: Gross margin | J1: Op margin
A2: 2026-07-31 | B2: 1470897000 | C2: 1096895000 | D2: -33232000 | E2: 5306000 | F2: 530268000 | G2: -153932000 | H2: 376336000 | I2: =IF(B2,C2/B2,"") | J2: =IF(B2,D2/B2,"")
A3: 2026-04-30 | B3: 1385629000 | C3: 1043352000 | D3: -30600000 | E3: 27774000 | F3: 590937000 | G3: -120195000 | H3: 470742000 | I3: =IF(B3,C3/B3,"") | J3: =IF(B3,D3/B3,"")
A4: 2026-01-31 | B4: 1305375000 | C4: 993677000 | D4: 13786000 | E4: 59377000 | F4: 497869000 | G4: -119720000 | H4: 378149000 | I4: =IF(B4,C4/B4,"") | J4: =IF(B4,D4/B4,"")
A5: 2025-10-31 | B5: 1234244000 | C5: 926439000 | D5: -69443000 | E5: -33997000 | F5: 397541000 | G5: -100165000 | H5: 297376000 | I5: =IF(B5,C5/B5,"") | J5: =IF(B5,D5/B5,"")
A6: 2025-07-31 | B6: 1168952000 | C6: 860401000 | D6: -105457000 | E6: -70153000 | F6: 332832000 | G6: -47786000 | H6: 285046000 | I6: =IF(B6,C6/B6,"") | J6: =IF(B6,D6/B6,"")

Sheet Sources
A1: Item | B1: Value | C1: Source & timestamp
A2: Price 股价 | B2: 263.01 | C2: Yahoo Finance quote, fetched 2026-10-13T18:12 SGT
A3: Market cap 市值 | B3: 269305118720 | C3: Yahoo info.marketCap 2026-10-13T18:12
A4: Cash 现金 | B4: 5013847040 | C4: Yahoo info.totalCash (latest filing) 2026-10-13T18:12
A5: Debt 负债 | B5: 820179008 | C5: Yahoo info.totalDebt (latest filing) 2026-10-13T18:12
A6: Revenue TTM 收入 | B6: 5396145152 | C6: Yahoo info.totalRevenue (TTM, USD) 2026-10-13T18:12
A7: FCF TTM 自由现金流 | B7: 1522603000 | C7: Sum of last 4 quarterly FCF (q_cash); quarters ['2026-07-31', '2026-04-30', '2026-01-31', '2025-10-31'] (USD)
A8: Beta | B8: 1.197 | C8: Yahoo info.beta (5Y monthly)
A9: Risk-free 10Y 无风险利率 | B9: 0.0522 | C9: FRED DGS10 2026-10-08
A10: FX USD per USD | B10: 1 | C10: n/a (USD)
A11: Consensus rev growth FY0 | B11: 0.2482 | C11: Yahoo revenue_estimate 0y
A12: Consensus rev growth FY+1 | B12: 0.22639999 | C12: Yahoo revenue_estimate +1y

Sheet Assumptions
A1: Assumption | B1: Value | C1: Rationale / class
A2: ERP 股权风险溢价 | B2: 0.05 | C2: ASSUMPTION: 5.0% house mature-market ERP
A3: Beta clamp | B3: [0.8,1.6] → 1.20 | C3: ASSUMPTION: limit extreme betas
A4: Tax rate (ROIC) | B4: 0.18 | C4: ASSUMPTION: blended cash tax 18%
A5: Year-1 growth (Base) | B5: 0.22639999 | C5: Consensus FY+1 revenue growth (Yahoo revenue_estimate '+1y'); capped at 100%
A6: Growth fade | B6: linear Y1→terminal by Y10 | C6: ASSUMPTION
A7: Starting FCF margin | B7: 0.28216494 | C7: DATA: FCF TTM / Revenue TTM, floored -50%
A8: Long-run FCF margin (Base) | B8: 0.32 | C8: ASSUMPTION (analyst framework, reached by Y5; see profile)
A9: Bear/Bull Y1 growth multiplier | B9: 0.5x / 1.3x | C9: ASSUMPTION
A10: Bear/Bull margin multiplier | B10: 0.8x / 1.15x | C10: ASSUMPTION
A11: WACC adj Bear/Bull | B11: +1.0pp / -0.5pp | C11: ASSUMPTION
A12: Terminal g Bear/Base/Bull | B12: 2.5% / 3.0% / 3.5% | C12: ASSUMPTION
A13: Scenario probabilities | B13: 25% / 50% / 25% | C13: ASSUMPTION
A14: Horizon exit EV/NTM-FCF Bear/Base/Bull | B14: 15x / 25x / 35x | C14: ASSUMPTION
A15: Per-share conversion | B15: value × fx ÷ market cap × price | C15: METHOD: avoids ADR/share-class mismatch
